[{"id":"1042063508","name":"Fazenda Santo Ângelo","tags":"aeroway:aerodrome,icao:SDAN,wikidata:Q31204955","lat":-22.2455559,"lng":-48.2577782},{"id":"2842475767","tags":"amenity:restaurant","lat":-22.2617727,"lng":-48.2346468},{"id":"2843093001","name":"tavolaro","tags":"amenity:restaurant","lat":-22.2627319,"lng":-48.2346112},{"id":"3291761160","tags":"shop:convenience","lat":-22.1751482,"lng":-48.4861818},{"id":"6390972057","tags":"amenity:restaurant","lat":-22.2632262,"lng":-48.2342988},{"id":"8410365058","name":"Rancho da Pamonha","tags":"addr:city:Brotas,addr:housenumber:Km 140,addr:postcode:17380-000,addr:street:Rodovia Engenheiro Paulo Nilo Romano,addr:suburb:Rod. Brotas - Bauru,amenity:restaurant","lat":-22.2653471,"lng":-48.2141094},{"id":"9364438331","name":"Cachoeira do Martello","tags":"amenity:restaurant","lat":-22.2909182,"lng":-48.2214506}]