[{"id":"530907052","name":"Casarão de Pedra","tags":"amenity:restaurant","lat":-14.1812609,"lng":-39.3181729},{"id":"5701807633","name":"Aldacy Santana mercadinho três irmã","tags":"addr:street:Rua operário marcelino,shop:supermarket","lat":-14.1632806,"lng":-39.3733519},{"id":"5701807634","name":"M raimunda do santos mercadinho so bênçãos","tags":"shop:supermarket","lat":-14.161689,"lng":-39.372923},{"id":"5701844521","name":"Lucineide de souza supermercado travessao","tags":"shop:supermarket","lat":-14.1495101,"lng":-39.3311602},{"id":"5703272722","name":"Aline","tags":"shop:supermarket","lat":-14.1143306,"lng":-39.256077},{"id":"5723394921","name":"N M Diogo minemercado millenium","tags":"addr:street:Travessão,shop:supermarket","lat":-14.1488848,"lng":-39.3311994},{"id":"5723394922","name":"Joselina santos cardoso mercado 3j","tags":"addr:street:Praca,shop:supermarket","lat":-14.1614066,"lng":-39.3693031},{"id":"6046702085","name":"Anita ferreira santana","tags":"addr:street:Avenida Rio Branco,shop:supermarket","lat":-14.1490411,"lng":-39.3312136},{"id":"6046704085","name":"M do N bastos","tags":"addr:street:Avenida Rio Branco,shop:supermarket","lat":-14.1502942,"lng":-39.3314752},{"id":"6695807485","name":"7284 elinor rosario","tags":"shop:supermarket","lat":-14.1504638,"lng":-39.3314855},{"id":"6766002393","name":"1277 edilene pereira Jesus","tags":"name:en:Mercearia universo,shop:supermarket","lat":-14.1626492,"lng":-39.3691267},{"id":"8520549019","name":"Restaurante Ilha Veneza","tags":"amenity:restaurant","lat":-14.1457885,"lng":-39.0904796}]