[{"id":"3372630975","name":"Rodoviária de Belo Jardim","tags":"amenity:bus_station,building:public","lat":-8.3433558,"lng":-36.4180037},{"id":"3372643756","name":"IFPE - Ginásio Poliesportivo","tags":"leisure:sports_centre,sport:multi","lat":-8.3219553,"lng":-36.4165045},{"id":"3372643758","name":"Refeitório","tags":"amenity:restaurant","lat":-8.3206068,"lng":-36.4164123},{"id":"3374976920","name":"Posto dos correios","tags":"amenity:post_office,operator:Correios,operator:wikidata:Q3375004,operator:wikipedia:en:Correios","lat":-8.3341067,"lng":-36.4204875},{"id":"3493825399","name":"Banco do Brasil","tags":"amenity:bank,brand:Banco do Brasil,brand:wikidata:Q610817,brand:wikipedia:en:Banco do Brasil","lat":-8.3364788,"lng":-36.4237623},{"id":"3493825400","name":"Caixa Econômica Federal","tags":"amenity:bank,brand:Caixa Econômica Federal,brand:wikidata:Q835283,brand:wikipedia:pt:Caixa Econômica Federal","lat":-8.3365876,"lng":-36.4230274},{"id":"3831734813","tags":"amenity:police","lat":-8.3272566,"lng":-36.4201076},{"id":"4444473089","name":"Banco do Nordeste","tags":"addr:housenumber:340,addr:street:Rua Tenente Cleto Campelo,amenity:bank,brand:Banco do Nordeste,brand:wikidata:Q4854137,brand:wikipedia:en:Banco do Nordeste,name:pt:Banco do Nordeste,opening_hours:Mo-Fr 10:00-15:00,phone:+55 81 3726-6421,website:https://www.bnb.gov.br/","lat":-8.3377746,"lng":-36.4273729},{"id":"4951643113","name":"Belo Jardim","tags":"public_transport:station,railway:station","lat":-8.3376736,"lng":-36.425351},{"id":"5070257125","name":"Loja conveniência santo expedito","tags":"addr:street:BR 232,name:pt:Loja conveniência santo expedito,opening_hours:24/7,shop:convenience","lat":-8.3292249,"lng":-36.2233743},{"id":"5070257127","tags":"addr:street:Acesso BR-232 Sentido Belo Jardim,amenity:restaurant","lat":-8.3464759,"lng":-36.3967161},{"id":"5258381403","name":"Colégio Águia","tags":"amenity:school","lat":-8.3281806,"lng":-36.4195305},{"id":"6563952486","name":"Tacaimbó","tags":"public_transport:station,railway:station,train:yes","lat":-8.3166014,"lng":-36.2893489}]