[{"id":"3627268928","name":"Churrascaria O Cervejao","tags":"addr:street:BR 343,amenity:restaurant,cuisine:steak_house;barbecue;regional,internet_access:wlan,internet_access:fee:no","lat":-4.8367558,"lng":-42.1815352},{"id":"4415134448","name":"Drogaria Santa Teresinha","tags":"amenity:pharmacy","lat":-4.8362693,"lng":-42.1814074},{"id":"4415134449","name":"Chiqueiro Bar","tags":"amenity:bar","lat":-4.8360898,"lng":-42.1811817},{"id":"4415172370","tags":"amenity:pharmacy","lat":-4.8361307,"lng":-42.1824017},{"id":"4415172371","name":"Comercial São Gonçalo","tags":"shop:supermarket","lat":-4.8363722,"lng":-42.1821968},{"id":"4415172372","name":"Dogueria BR","tags":"amenity:restaurant,cuisine:pizza;hot_dog;hot_dog;panelada;sarapatel;batata_frita,outdoor_seating:yes","lat":-4.8364716,"lng":-42.1820061},{"id":"4415172379","tags":"amenity:bar","lat":-4.8292227,"lng":-42.1664154},{"id":"4415173490","tags":"amenity:police","lat":-4.8271869,"lng":-42.1695073},{"id":"4415173492","tags":"amenity:library","lat":-4.8250929,"lng":-42.1683104},{"id":"4425370632","name":"Café na Roça","tags":"amenity:cafe,outdoor_seating:yes","lat":-4.8401411,"lng":-42.1766009},{"id":"4425370633","name":"Hawai Grill","tags":"amenity:restaurant,internet_access:wlan,internet_access:fee:no,outdoor_seating:yes,wheelchair:yes","lat":-4.8373522,"lng":-42.1731406},{"id":"4425370634","name":"João do Churrasco","tags":"amenity:restaurant,cuisine:steak_house;barbecue;chicken;regional","lat":-4.8413164,"lng":-42.1770294},{"id":"4425370667","tags":"amenity:nightclub","lat":-4.8367743,"lng":-42.1731271},{"id":"5830376380","name":"Praça do IBAMA","tags":"leisure:park","lat":-4.8341569,"lng":-42.1647923},{"id":"8017835742","name":"Drogaria Lindapharma","tags":"amenity:pharmacy,dispensing:yes,healthcare:pharmacy,opening_hours:Mo-Su 07:00-22:00,opening_hours:covid19:open","lat":-4.8360051,"lng":-42.1810223},{"id":"9495244116","name":"Esc Mun Dr Milton Soldani Afonso","tags":"amenity:school","lat":-4.8448166,"lng":-42.1816835},{"id":"9495273528","name":"Esc Espec Pedro Martins Neto","tags":"addr:city:Campo Maior,addr:housenumber:900,addr:postcode:64280-000,addr:street:Rua Mestre Miguel Rosa,addr:suburb:São Luis,amenity:school","lat":-4.8344604,"lng":-42.1789317},{"id":"9495275180","name":"Creche Mae Francisquinha","tags":"addr:city:Campo Maior,addr:postcode:64280-000,addr:street:Rua Zezinho Andrade,addr:suburb:São Luis,amenity:school,phone:+55 86 3252 2197","lat":-4.8337708,"lng":-42.180659},{"id":"9495381321","name":"Educandario Filhos De Maria","tags":"amenity:school","lat":-4.8231736,"lng":-42.1672024},{"id":"9495384725","name":"Esc Mun Professor Hilson Bona","tags":"addr:city:Campo Maior,addr:postcode:64280-000,addr:street:Rua Senador José Euzébio,addr:suburb:Centro,amenity:school","lat":-4.8240636,"lng":-42.1686266},{"id":"9495395950","name":"Creche Tio Achiles","tags":"addr:city:Campo Maior,addr:postcode:64280-000,addr:street:Rua Doutor Pedro Teixeira,addr:suburb:Centro,amenity:school","lat":-4.8272414,"lng":-42.1700482},{"id":"9495404717","name":"Instituto De Ensino Intellectus","tags":"addr:city:Campo Maior,addr:housenumber:241,addr:postcode:64280-000,addr:street:Rua Antonino Freire,addr:suburb:Centro,amenity:school","lat":-4.8250097,"lng":-42.1643673},{"id":"9495538422","name":"Escola Municipal Abdias Saboia","tags":"amenity:school","lat":-4.8313387,"lng":-41.8871932},{"id":"9495548208","name":"Escola Municipal Monsenhor Silvestre Felix","tags":"amenity:school","lat":-4.8063888,"lng":-41.9742201},{"id":"9495558487","name":"Esc Mun Mano Castelo Branco","tags":"amenity:school","lat":-4.7663815,"lng":-41.9989689},{"id":"9495559549","name":"Escola Municipal Rafael Nogueira Passos","tags":"amenity:school","lat":-4.8295907,"lng":-42.0021687},{"id":"9496233740","name":"Esc Mun Vida Verde","tags":"amenity:school","lat":-4.834569,"lng":-42.1641001},{"id":"9496320007","name":"Esc Mun Nossa Senhora De Fatima","tags":"addr:city:Campo Maior,addr:postcode:64280-000,addr:street:Rua Comendador Jacob de Almendra,addr:suburb:Fátima,amenity:school","lat":-4.839378,"lng":-42.1686347},{"id":"9496331694","name":"U E Valdivino Tito","tags":"addr:city:Campo Maior,addr:housenumber:464,addr:postcode:64280-000,addr:street:Avenida José Paulino,addr:suburb:Centro,amenity:school","lat":-4.8272124,"lng":-42.1643721},{"id":"9496361689","name":"Colegio Alfabetoc","tags":"addr:city:Campo Maior,addr:housenumber:598,addr:postcode:64280-000,addr:street:Avenida José Paulino,addr:suburb:Centro,amenity:school","lat":-4.8269341,"lng":-42.1648689},{"id":"9496432678","name":"Creche Tia Angelica","tags":"amenity:school","lat":-4.8185017,"lng":-42.1844436},{"id":"9496437809","name":"Esc Mun Aguida Maria Da Conceicao","tags":"amenity:school","lat":-4.8068324,"lng":-42.1186624}]