[{"id":"441020942","name":"Churrascaria Barranco","tags":"addr:housenumber:1578,addr:street:Avenida Protásio Alves,addr:suburb:Alto Petrópolis,amenity:restaurant,cuisine:barbecue,description:A lista de clássicos no Barranco é tão extensa quanto a quilometragem do carrinho de saladas: a polentinha, o lombo com queijo, a picanha à Barranco, o filé à parmegiana. Aniversários em família nas mesas na rua são programas mais que completos.,opening_hours:Mo-Su 11:30-01:00,phone:+55 51 3331-6172,website:http://www.churrascariabarranco.com.br/,wheelchair:limited","lat":-30.0405812,"lng":-51.1922847},{"id":"455006661","tags":"shop:convenience","lat":-30.050105,"lng":-51.1868061},{"id":"529555700","name":"Marostika II","tags":"amenity:restaurant,wheelchair:no","lat":-30.017987,"lng":-51.1959658},{"id":"595759508","name":"Gecepel","tags":"shop:supermarket","lat":-30.0393598,"lng":-51.1620554},{"id":"783667501","tags":"amenity:parking","lat":-30.019253,"lng":-51.1633032},{"id":"783667502","tags":"amenity:parking","lat":-30.0187827,"lng":-51.1642722},{"id":"842658544","name":"Mini Mercado Ponto Verde","tags":"addr:city:Porto Alegre,addr:housenumber:1677,addr:postcode:90460-001,addr:street:Avenida Coronel Lucas de Oliveira,addr:suburb:Petrópolis,shop:supermarket","lat":-30.0374133,"lng":-51.1946957},{"id":"842659487","name":"Usina do Espetinho","tags":"addr:city:Porto Alegre,addr:housenumber:1671,addr:postcode:90460-001,addr:street:Avenida Coronel Lucas de Oliveira,addr:suburb:Petrópolis,amenity:restaurant,capacity:50,cuisine:Churrasuinho,_Pizza,_Cachurrasco_e_Bauru,opening_hours:Mo-Sa 17:00-23:00,smoking:outside,takeaway:yes","lat":-30.0373504,"lng":-51.1946487},{"id":"842662640","name":"Shell","tags":"amenity:fuel,brand:Shell,brand:wikidata:Q154950,brand:wikipedia:en:Shell plc,shop:convenience","lat":-30.0330546,"lng":-51.1955016},{"id":"954713595","name":"Fornão","tags":"amenity:restaurant,website:http://www.fornao-rs.com.br,wheelchair:no","lat":-30.0428723,"lng":-51.1904429},{"id":"1139635837","name":"Itaú","tags":"addr:street:Avenida Carlos Gomes,amenity:bank,atm:yes,brand:Itaú Unibanco,brand:wikidata:Q1424293,brand:wikipedia:pt:Itaú Unibanco,operator:Itaú","lat":-30.0252695,"lng":-51.1831257},{"id":"1139635942","name":"Bradesco","tags":"addr:street:Avenida Carlos Gomes,amenity:bank,atm:yes,brand:Bradesco,brand:wikidata:Q806181,brand:wikipedia:en:Banco Bradesco,name:fr:Bradesco,operator:HSBC","lat":-30.0234863,"lng":-51.184034},{"id":"1139636400","name":"La Jolla Cozinha Artesanal","tags":"amenity:restaurant,old_name:Solar Carlos Gomes","lat":-30.0260696,"lng":-51.1827224},{"id":"1139636552","name":"Estética Felipe Nuñez","tags":"shop:beauty","lat":-30.0351714,"lng":-51.1809899},{"id":"1139968417","name":"Shopping Iguatemi","tags":"entrance:yes,shop:supermarket","lat":-30.0268257,"lng":-51.1623591},{"id":"1139972320","name":"Panvel","tags":"amenity:pharmacy,brand:Panvel,brand:wikidata:Q10344254,brand:wikipedia:pt:Panvel,healthcare:pharmacy","lat":-30.028462,"lng":-51.1699793},{"id":"1139972437","name":"Guacamole","tags":"addr:housenumber:165,addr:street:Rua Desembargador Augusto Loureiro Lima,amenity:restaurant,contact:email:contato@guacamolemex.com.br,contact:facebook:https://www.facebook.com/guacamolepoa/,contact:instagram:https://www.instagram.com/guacamolemex/,contact:phone:+55 51 2112-8844,cuisine:mexican,delivery:yes,diet:vegan:yes,diet:vegetarian:yes,website:http://www.guacamolemex.com.br/","lat":-30.0317182,"lng":-51.1834967},{"id":"1149305790","name":"Casa do Camarão","tags":"amenity:restaurant","lat":-30.0279684,"lng":-51.1695791},{"id":"1149306135","name":"Magistrallis Farmácia de Manipulação","tags":"amenity:pharmacy,healthcare:pharmacy","lat":-30.0271232,"lng":-51.1815134},{"id":"1149306462","name":"Esta Fácil","tags":"amenity:parking,capacity:50,fee:R$8,00 - 30mins,layer:-1,old_name:Express Park,parking:underground,supervised:yes","lat":-30.0259858,"lng":-51.1822721},{"id":"1286851292","name":"Centro de Ensino e Treinamento em Saúde","tags":"amenity:school","lat":-30.0382982,"lng":-51.168094},{"id":"1286851348","name":"Pet Center B & N","tags":"addr:housenumber:1066,addr:street:Avenida Teixeira Mendes,shop:pet,website:http://www.petcenterben.com.br","lat":-30.0306719,"lng":-51.1663091},{"id":"1286851368","name":"Vet Integralle","tags":"shop:pet","lat":-30.0308249,"lng":-51.1663427},{"id":"1286851394","name":"Open Matt: Jiu Jitsu e Associados","tags":"leisure:sports_centre,sport:gymnastics","lat":-30.0379623,"lng":-51.1683858},{"id":"1286851509","name":"Posto da praça","tags":"amenity:fuel,brand:Ipiranga,operator:Ipiranga,shop:convenience","lat":-30.0351807,"lng":-51.1648403},{"id":"1398746510","name":"Farmais","tags":"amenity:pharmacy,healthcare:pharmacy","lat":-30.0272691,"lng":-51.1897886},{"id":"1398746511","name":"Panvel","tags":"addr:street:Rua Anita Garibaldi,amenity:pharmacy,brand:Panvel,brand:wikidata:Q10344254,brand:wikipedia:pt:Panvel,healthcare:pharmacy","lat":-30.0266953,"lng":-51.1898516},{"id":"1398746516","name":"Santander","tags":"addr:street:Rua Anita Garibaldi,amenity:bank,brand:Santander,brand:wikidata:Q5835668,brand:wikipedia:en:Santander Bank,operator:Santander","lat":-30.0266953,"lng":-51.1894332},{"id":"1412440004","name":"Estacionamento Guanabara","tags":"amenity:parking,capacity:30,int_name:Guanabara Car Parking","lat":-30.0564367,"lng":-51.1627187},{"id":"1423330153","name":"Mãe de Deus Center","tags":"addr:street:Avenida Soledade,amenity:hospital,emergency:yes,healthcare:hospital","lat":-30.0327042,"lng":-51.1781895},{"id":"1518530237","name":"Supermercado Bampi","tags":"addr:housenumber:779,addr:street:Rua Doutor Jorge Fayet,opening_hours:Mo-Fr 08:30-12:00,14:00-20:00; Sa 08:30-13:00,15:00-20:00; Su 09:30-12:30,phone:+55 51 3334-3519,shop:supermarket","lat":-30.0358958,"lng":-51.1619917},{"id":"1676252678","name":"Restaurante Metropole","tags":"addr:postcode:90440-150,addr:street:Rua Felipe Neri,amenity:restaurant,cuisine:international","lat":-30.0234083,"lng":-51.192701},{"id":"1721291518","name":"HSBC","tags":"amenity:bank,atm:yes,brand:HSBC,brand:wikidata:Q190464,brand:wikipedia:en:HSBC","lat":-30.0579473,"lng":-51.1736605},{"id":"1721291533","name":"Restaurante Universitário","tags":"amenity:restaurant,cuisine:regional","lat":-30.0568981,"lng":-51.1725085},{"id":"1721291535","name":"Banco do Brasil","tags":"amenity:bank,atm:yes,brand:Banco do Brasil,brand:wikidata:Q610817,brand:wikipedia:en:Banco do Brasil","lat":-30.0577093,"lng":-51.1729899},{"id":"1721291537","name":"Banrisul","tags":"amenity:bank,atm:yes,brand:Banrisul,brand:wikidata:Q4857098,brand:wikipedia:en:Banrisul","lat":-30.0577406,"lng":-51.1736591},{"id":"1721291547","name":"Restaurante Sabor Família","tags":"amenity:restaurant,cuisine:regional","lat":-30.0567564,"lng":-51.1725157},{"id":"1721291548","name":"Lancheria do 5","tags":"amenity:restaurant,diet:vegan:yes","lat":-30.0577283,"lng":-51.1732243},{"id":"1723383448","tags":"amenity:car_wash","lat":-30.0563742,"lng":-51.1686373},{"id":"1756347897","name":"Banco do Brasil","tags":"addr:street:Avenida Protásio Alves,amenity:bank,atm:yes,brand:Banco do Brasil,brand:wikidata:Q610817,brand:wikipedia:en:Banco do Brasil,wheelchair:yes","lat":-30.0434453,"lng":-51.1816997},{"id":"1786937992","tags":"leisure:sports_centre","lat":-30.0253572,"lng":-51.1905642},{"id":"1786937993","tags":"leisure:sports_centre","lat":-30.0266275,"lng":-51.1897408},{"id":"1786938565","tags":"amenity:bank","lat":-30.0251506,"lng":-51.1899688},{"id":"1786938801","tags":"amenity:car_wash","lat":-30.0271732,"lng":-51.1896791},{"id":"1786938802","tags":"amenity:pharmacy,healthcare:pharmacy","lat":-30.0270548,"lng":-51.1895289},{"id":"1786938803","tags":"shop:convenience","lat":-30.0271082,"lng":-51.1896174},{"id":"1786939616","tags":"amenity:bar","lat":-30.0246322,"lng":-51.1901172},{"id":"1786939617","tags":"amenity:restaurant","lat":-30.0258263,"lng":-51.1903307},{"id":"2079152319","name":"Itaú","tags":"addr:housename:Carlos Gomes Center,addr:housenumber:550,addr:street:Avenida Soledade,amenity:bank,branch:BBA,brand:Itaú Unibanco,brand:wikidata:Q1424293,brand:wikipedia:pt:Itaú Unibanco","lat":-30.0322682,"lng":-51.1785268},{"id":"2079153088","name":"Santander","tags":"addr:housename:Carlos Gomes Center,addr:housenumber:550,addr:street:Avenida Soledade,amenity:bank,brand:Santander,brand:wikidata:Q5835668,brand:wikipedia:en:Santander Bank","lat":-30.0322503,"lng":-51.1784867},{"id":"2079157061","name":"De Lage Landen","tags":"addr:housename:Carlos Gomes Center,addr:housenumber:550,addr:street:Avenida Soledade,amenity:bank","lat":-30.0322304,"lng":-51.1784551},{"id":"2079157414","name":"Banco24Horas","tags":"amenity:atm,brand:Banco24Horas,brand:wikidata:Q4854069,brand:wikipedia:pt:Banco24Horas,operator:Banco 24 Horas","lat":-30.0326276,"lng":-51.1782674},{"id":"2079160685","name":"Emporio Restaurante","tags":"addr:street:Avenida Soledade,amenity:restaurant","lat":-30.0326839,"lng":-51.1783407},{"id":"2079162140","name":"Itaú","tags":"amenity:bank,atm:yes,brand:Itaú Unibanco,brand:wikidata:Q1424293,brand:wikipedia:pt:Itaú Unibanco","lat":-30.032792,"lng":-51.1789152},{"id":"2083053508","tags":"addr:street:Avenida Protásio Alves,amenity:pharmacy,healthcare:pharmacy","lat":-30.043527,"lng":-51.1826662},{"id":"2418114259","name":"3ª Companhia 11º BPM","tags":"alt_name:3a Companhia 11o BPM,amenity:police,official_name:Terceira Companhia - Décimo Primeiro Batalhão da Polícia Militar,phone:+55 51 3334-1843","lat":-30.03468,"lng":-51.1639718},{"id":"2435886511","name":"Caixa Econômica Federal","tags":"addr:street:Avenida Carlos Gomes,amenity:bank,atm:yes,brand:Caixa Econômica Federal,brand:wikidata:Q835283,brand:wikipedia:pt:Caixa Econômica Federal","lat":-30.0247943,"lng":-51.1829399},{"id":"2447626990","tags":"amenity:parking","lat":-30.0252659,"lng":-51.1617681},{"id":"2455822573","name":"Safe Park","tags":"amenity:parking,capacity:50,fee:yes,parking:multi-storey,supervised:yes","lat":-30.0252184,"lng":-51.1830819},{"id":"2460997296","tags":"amenity:parking,fee:yes,park_ride:yes,supervised:no","lat":-30.0273704,"lng":-51.1792842},{"id":"2460997297","tags":"amenity:parking,fee:yes,park_ride:yes,supervised:no","lat":-30.0269682,"lng":-51.1794519},{"id":"2461647867","name":"Correios","tags":"addr:housenumber:598,addr:street:Avenida Carlos Gomes,amenity:post_office,brand:Correios,brand:wikidata:Q3375004,brand:wikipedia:en:Correios,operator:Correios,operator:wikidata:Q3375004,operator:wikipedia:en:Correios","lat":-30.0270102,"lng":-51.1817507},{"id":"2506179597","name":"Bradesco","tags":"addr:street:Avenida Carlos Gomes,amenity:bank,atm:yes,branch:Prime,brand:Bradesco,brand:wikidata:Q806181,brand:wikipedia:en:Banco Bradesco,operator:Bradesco","lat":-30.0247299,"lng":-51.1834326},{"id":"2506179598","name":"Maxxi Econômica Farmácia","tags":"addr:street:Avenida Carlos Gomes,amenity:pharmacy,healthcare:pharmacy","lat":-30.0254637,"lng":-51.1830357},{"id":"2510453094","name":"Bar Inglês","tags":"alt_name:Buraco 19,amenity:bar","lat":-30.0251973,"lng":-51.1712231},{"id":"2532124920","name":"Bier Garten","tags":"amenity:restaurant","lat":-30.0282905,"lng":-51.1850523},{"id":"2558893367","name":"Restaurante Universitário","tags":"amenity:restaurant","lat":-30.0505205,"lng":-51.1822839},{"id":"2641007673","name":"Z Café Bella Vista","tags":"addr:city:90460-050,addr:housename:Lojas 2 e 3,addr:housenumber:543,addr:street:Avenida Nilópolis,amenity:cafe,opening_hours:Su-Th 09:30-00:00; Fr-Sa 09:30-01:30,phone:+55 51 3029-6490,start_date:2005,website:http://www.zcafe.com.br/,wheelchair:yes","lat":-30.0367029,"lng":-51.1864314},{"id":"2697121784","name":"Agafarma","tags":"amenity:pharmacy,brand:Agafarma,brand:wikidata:Q93735939,dispensing:no,healthcare:pharmacy","lat":-30.0425225,"lng":-51.1910201},{"id":"2697121785","name":"Banco do Brasil","tags":"amenity:bank,atm:yes,brand:Banco do Brasil,brand:wikidata:Q610817,brand:wikipedia:en:Banco do Brasil,wheelchair:yes","lat":-30.0408176,"lng":-51.1692318},{"id":"2697121793","name":"Banrisul","tags":"amenity:bank,atm:yes,brand:Banrisul,brand:wikidata:Q4857098,brand:wikipedia:en:Banrisul,wheelchair:yes","lat":-30.0413484,"lng":-51.1560809},{"id":"2697121794","name":"Bradesco","tags":"addr:street:Avenida Protásio Alves,amenity:bank,atm:yes,brand:Bradesco,brand:wikidata:Q806181,brand:wikipedia:en:Banco Bradesco,wheelchair:yes","lat":-30.0425594,"lng":-51.1795563},{"id":"2697121797","name":"Churrascaria São Rafael","tags":"addr:housenumber:3284,addr:postcode:90410-007,addr:street:Avenida Protásio Alves,amenity:restaurant,cuisine:barbecue,phone:+55 51 3334-7155,wheelchair:limited","lat":-30.0403411,"lng":-51.1772339},{"id":"2697121798","name":"Correios","tags":"amenity:post_office,operator:Correios,operator:wikidata:Q3375004,operator:wikipedia:en:Correios,wheelchair:limited","lat":-30.0407829,"lng":-51.1690311},{"id":"2697121802","name":"Gecepel","tags":"shop:supermarket","lat":-30.0397688,"lng":-51.1622872},{"id":"2697121808","name":"Itaú","tags":"amenity:bank,atm:yes,brand:Itaú Unibanco,brand:wikidata:Q1424293,brand:wikipedia:pt:Itaú Unibanco,wheelchair:yes","lat":-30.039713,"lng":-51.1625339},{"id":"2697121809","name":"Itaú","tags":"amenity:bank,atm:yes,brand:Itaú Unibanco,brand:wikidata:Q1424293,brand:wikipedia:pt:Itaú Unibanco,wheelchair:yes","lat":-30.0400331,"lng":-51.1961647},{"id":"2697121810","name":"Itaú","tags":"amenity:bank,atm:yes,brand:Itaú Unibanco,brand:wikidata:Q1424293,brand:wikipedia:pt:Itaú Unibanco,wheelchair:yes","lat":-30.0436354,"lng":-51.1834071},{"id":"2697121813","name":"Minimercado Santa Rita","tags":"addr:housenumber:3262,addr:street:Avenida Protásio Alves,shop:convenience","lat":-30.0405309,"lng":-51.177411},{"id":"2697121814","name":"Pedrini","tags":"addr:street:Av. Protásio Alves, 1472 - Alto Petrópolis, Porto Alegre - RS, 90410-005,amenity:restaurant,description:Bar e restaurante moderno com mesas externas que oferece comida de botequim e pratos brasileiros desde 1960.,opening_hours:Mo-Sa 17:00-02:00, 09:00-18:00; Su 12:00-01:00,phone:+55 51 3072-2790,wheelchair:yes","lat":-30.0403664,"lng":-51.1933413},{"id":"2697121817","name":"Santander","tags":"addr:street:Avenida Protásio Alves,amenity:bank,atm:yes,brand:Santander,brand:wikidata:Q5835668,brand:wikipedia:en:Santander Bank,wheelchair:yes","lat":-30.0393508,"lng":-51.1765994},{"id":"2697121821","name":"Supermercado Chico","tags":"shop:supermarket","lat":-30.0400951,"lng":-51.1648193},{"id":"2697121826","tags":"addr:street:Avenida Protásio Alves,amenity:parking","lat":-30.040929,"lng":-51.1774027},{"id":"2697121827","tags":"amenity:pharmacy,dispensing:no,healthcare:pharmacy","lat":-30.0401242,"lng":-51.1650373},{"id":"2697121832","name":"Banco24Horas","tags":"amenity:atm,brand:Banco24Horas,brand:wikidata:Q4854069,brand:wikipedia:pt:Banco24Horas,operator:Banco 24 Horas","lat":-30.0397966,"lng":-51.1621906},{"id":"2764106783","name":"Restaurante do 50","tags":"amenity:restaurant,cuisine:regional","lat":-30.0577498,"lng":-51.1722407},{"id":"2783655568","name":"Parilla del Sur","tags":"addr:housenumber:111,addr:street:Avenida Nilópolis,amenity:restaurant,cuisine:uruguayan,phone:+55 51 3012-7878,website:https://parrilladelsur.com.br/site/,wheelchair:yes","lat":-30.0386558,"lng":-51.1907895},{"id":"2783655617","name":"Banrisul","tags":"amenity:bank,atm:yes,brand:Banrisul,brand:wikidata:Q4857098,brand:wikipedia:en:Banrisul","lat":-30.0150749,"lng":-51.1595423},{"id":"2884349759","name":"Panvel","tags":"amenity:pharmacy,brand:Panvel,brand:wikidata:Q10344254,brand:wikipedia:pt:Panvel,healthcare:pharmacy","lat":-30.0202516,"lng":-51.1812104},{"id":"2884349760","name":"Banco24Horas","tags":"amenity:atm,brand:Banco24Horas,brand:wikidata:Q4854069,brand:wikipedia:pt:Banco24Horas,check_date:2020-12-16,drive_through:no,layer:-1,operator:Tecban","lat":-30.0202894,"lng":-51.1805042},{"id":"2884349761","name":"Banrisul","tags":"amenity:atm,brand:Banrisul,brand:wikidata:Q4857098,brand:wikipedia:en:Banrisul,check_date:2020-12-16,drive_through:no,layer:-1,operator:Banrisul,operator:wikidata:Q4857098,operator:wikipedia:en:Banrisul","lat":-30.0202892,"lng":-51.1804892},{"id":"2884349762","name":"Banco do Brasil","tags":"amenity:atm,brand:Banco do Brasil,brand:wikidata:Q610817,brand:wikipedia:en:Banco do Brasil,check_date:2020-12-16,drive_through:no,layer:-1,operator:Banco do Brasil,operator:wikidata:Q610817,operator:wikipedia:en:Banco do Brasil","lat":-30.0202686,"lng":-51.1804898},{"id":"2961774275","name":"Bella Gulla","tags":"amenity:cafe","lat":-30.0202885,"lng":-51.180615},{"id":"2989737455","tags":"addr:street:Alameda Raimundo Correa,amenity:restaurant","lat":-30.0265583,"lng":-51.1800788},{"id":"2994579938","name":"Banrisul","tags":"addr:housenumber:1800,addr:street:Avenida Bento Gonçalves,amenity:bank,atm:yes,brand:Banrisul,brand:wikidata:Q4857098,brand:wikipedia:en:Banrisul,operator:Banrisul,wheelchair:yes","lat":-30.0573613,"lng":-51.1960466},{"id":"2994579951","name":"Santander","tags":"addr:city:Porto Alegre,addr:housenumber:1924,addr:postcode:90650-003,addr:street:Avenida Bento Gonçalves,addr:suburb:Partenon,amenity:bank,atm:yes,brand:Santander,brand:wikidata:Q5835668,brand:wikipedia:en:Santander Bank,operator:Santander,wheelchair:yes","lat":-30.0580081,"lng":-51.1950679},{"id":"3086422921","name":"Sushi Seninha","tags":"addr:housenumber:32,addr:street:Rua Felizardo Furtado,amenity:restaurant,cuisine:japanese,phone:+55 51 3084-9555,website:http://sushiseninha.com.br","lat":-30.0440547,"lng":-51.1836479},{"id":"3086422923","name":"Pueblo","tags":"addr:housenumber:147,addr:postcode:90460-200,addr:street:Avenida Ijuí,amenity:restaurant,cuisine:mexican,description:Restaurante aconchegante que serve nachos, tacos, burritos e fajitas entre outras especialidades mexicanas. Para acompanhar, margaritas, mojitos, cervejas e uma carta de bebidas que inclui drinks autorais.,opening_hours:Mo-Fr 11:30-14:00, 19:00-00:00; Sa, Su 12:00-15:00, 19:00-00:00,phone:+55 51 3332-5540,website:http://www.restaurantepueblo.com.br/","lat":-30.0423366,"lng":-51.1857266},{"id":"3107987354","name":"Itaú","tags":"addr:street:Avenida Carlos Gomes,amenity:bank,atm:yes,branch:Personnalité,brand:Itaú Unibanco,brand:wikidata:Q1424293,brand:wikipedia:pt:Itaú Unibanco","lat":-30.0336628,"lng":-51.1781278},{"id":"3148960378","name":"Mercado Ferrari & Obalski","tags":"addr:housenumber:75,addr:street:Rua Barão de Ubá,shop:convenience,wheelchair:limited","lat":-30.0369927,"lng":-51.1930268},{"id":"3195814839","name":"Porto dos Filés","tags":"addr:housenumber:3226,addr:postcode:90410-007,addr:street:Avenida Protásio Alves,amenity:restaurant,phone:+55 51 3381-9362,website:http://www.portodosfiles.com.br/","lat":-30.040734,"lng":-51.177625},{"id":"3205080200","name":"Saikô","tags":"addr:city:Porto Alegre,addr:housenumber:668,addr:street:Avenida Ijuí,amenity:restaurant,cuisine:japanese,email:saiko@terra.com.br,phone:+55 51 3333-5533","lat":-30.0379121,"lng":-51.1877935},{"id":"3228695687","name":"Hashi Art Cuisine","tags":"addr:housenumber:151,addr:street:Rua Desembargador Augusto Loureiro Lima,amenity:restaurant,cuisine:japanese,opening_hours:19:30 - 00:00,phone:+55 51 3328-0005,website:http://www.hashi.com.br/,wheelchair:no","lat":-30.0318274,"lng":-51.1834209},{"id":"3250932102","tags":"shop:convenience","lat":-30.0461779,"lng":-51.18855},{"id":"3295535191","name":"Escola Maurício Sirotsky Sobrinho","tags":"addr:housenumber:59,addr:postcode:90620-280,addr:street:Padre Caldas,amenity:school,contact:email:efmauriciossobrinho-01cre@seduc.rs.gov.br,contact:phone:+55 51 3339-6598,official_name:Escola Estadual de Ensino Fundamental Maurício Sirotsky Sobrinho,short_name:EEEF Maurício Sirotsky Sobrinho","lat":-30.0576536,"lng":-51.1932496},{"id":"3369300030","tags":"amenity:post_office","lat":-30.0434317,"lng":-51.1819191},{"id":"3369313966","tags":"amenity:restaurant","lat":-30.0465484,"lng":-51.1782731},{"id":"3409878235","name":"Il Giardinetto","tags":"addr:housenumber:246,addr:street:Avenida Palmeira,amenity:restaurant,cuisine:pizza,phone:+55 51 3377-1313,website:http://www.ilgiardinetto.com.br/","lat":-30.0384802,"lng":-51.178997},{"id":"3590712027","tags":"amenity:library","lat":-30.0505023,"lng":-51.1834232},{"id":"3590752332","name":"Escola Visconde de Pelotas","tags":"addr:housenumber:200,addr:postcode:90450-170,addr:street:Rua Artur Rocha,amenity:school,contact:email:eeviscon@gmail.com,contact:phone:+55 51 3332-1238,official_name:Escola Estadual de Ensino Fundamental Visconde de Pelotas,short_name:EEEF Visconde de Pelotas","lat":-30.0248199,"lng":-51.1884116},{"id":"3605731037","name":"Sharin","tags":"addr:housenumber:332,addr:street:Rua Felipe Neri,amenity:restaurant,cuisine:indian,opening_hours:Mo-Sa 11:00-14:30,19:30-23:45,phone:+55 51 3333-8596,website:http://www.sharin.com.br","lat":-30.0228707,"lng":-51.1922987},{"id":"3734907626","name":"Hipermercado Bourbon Ipiranga","tags":"addr:city:Porto Alegre,addr:housenumber:5200,addr:postcode:90610-000,addr:street:Avenida Ipiranga,operator:Zaffari Bourbon,shop:supermarket,wheelchair:yes","lat":-30.0548913,"lng":-51.187348},{"id":"3735357468","name":"Le Bistrot","tags":"addr:city:Porto Alegre,addr:housenumber:22,addr:postcode:91340-310,addr:street:Alameda Alípio César,addr:suburb:Boa Vista,amenity:restaurant,wheelchair:no","lat":-30.0263915,"lng":-51.1782899},{"id":"3735357471","name":"Xavier 260","tags":"addr:city:Porto Alegre,addr:housenumber:260,addr:postcode:90540-110,addr:street:Rua Auxiliadora,addr:suburb:Auxiliadora,amenity:restaurant,cuisine:international,description:Cozinha tradicional catalã, apoiada em técnicas contemporâneas e ingredientes gaúchos, e ambiente sofisticado.R$ 130 por pessoa,opening_hours:Tu-Sa 20:00-23:00; Su 12:30-15:00,website:https://xavier.restaurant,wheelchair:no","lat":-30.0214913,"lng":-51.1908508},{"id":"3739505823","name":"Banrisul","tags":"amenity:bank,brand:Banrisul,brand:wikidata:Q4857098,brand:wikipedia:en:Banrisul,operator:Banco do Estado do Rio Grande do Sul,wheelchair:yes","lat":-30.0436514,"lng":-51.183481},{"id":"3739888301","name":"UpTime Escola de Idiomas","tags":"amenity:school","lat":-30.0149137,"lng":-51.1547981},{"id":"3798783552","name":"Panvel","tags":"addr:street:Avenida Cristóvão Colombo,amenity:pharmacy,brand:Panvel,brand:wikidata:Q10344254,brand:wikipedia:pt:Panvel,healthcare:pharmacy","lat":-30.0178509,"lng":-51.1905789},{"id":"3827293590","name":"Pizza Hut","tags":"amenity:restaurant,brand:Pizza Hut,brand:wikidata:Q191615,brand:wikipedia:en:Pizza Hut,cuisine:pizza","lat":-30.0422935,"lng":-51.1791067},{"id":"3844519524","name":"Bar 3","tags":"amenity:restaurant,cuisine:regional","lat":-30.0566578,"lng":-51.1721776},{"id":"3859797173","name":"Armazém Nobel","tags":"addr:city:Porto Alegre,addr:housenumber:9,addr:street:Rua Barão de Ubá,shop:supermarket,website:http://www.armazemnobel.com/","lat":-30.0375841,"lng":-51.193025},{"id":"3975080689","tags":"amenity:pharmacy,healthcare:pharmacy","lat":-30.0500826,"lng":-51.1865528},{"id":"3975080690","tags":"amenity:restaurant","lat":-30.0510374,"lng":-51.1872923},{"id":"3975080691","tags":"shop:convenience","lat":-30.0502426,"lng":-51.1865898},{"id":"3975080692","tags":"shop:pet","lat":-30.0498292,"lng":-51.1864357},{"id":"3975080695","tags":"shop:convenience","lat":-30.0503253,"lng":-51.1851817},{"id":"3975080700","name":"Cervo","tags":"shop:books","lat":-30.0522934,"lng":-51.1880681},{"id":"4113113825","name":"Feito de Sorvete","tags":"amenity:cafe,cuisine:ice_cream,website:http://www.feitodesorvete.com.br/,wheelchair:no","lat":-30.0365216,"lng":-51.1932748},{"id":"4114752002","name":"Compania Tudo Sobre o Pão","tags":"addr:housenumber:105,addr:street:Rua Jaraguá,amenity:restaurant,cuisine:burger,description:É um misto de padaria e sanduicheria artesanal, que fica em uma casinha muito simpática. Da cozinha, saem combinações incríveis, todas preparadas com ingredientes artesanais. Nossa dica é o Burger, com queijo colonial, bacon e tomates assados.,opening_hours:Mo-Sa 17:00-23:00,phone:+55 51 3024-2855,takeaway:yes","lat":-30.0368631,"lng":-51.1920275},{"id":"4121873779","name":"Valkiria Café","tags":"addr:housenumber:604,addr:street:Avenida Carlos Gomes,amenity:cafe,smoking:no","lat":-30.0271041,"lng":-51.1817012},{"id":"4121873781","name":"Banco do Brasil","tags":"addr:housenumber:1667,addr:street:Avenida Carlos Gomes,amenity:bank,brand:Banco do Brasil,brand:wikidata:Q610817,brand:wikipedia:en:Banco do Brasil","lat":-30.0355769,"lng":-51.1772473},{"id":"4121873782","name":"Santander","tags":"addr:street:Avenida Carlos Gomes,amenity:bank,brand:Santander,brand:wikidata:Q5835668,brand:wikipedia:en:Santander Bank","lat":-30.0358138,"lng":-51.1770113},{"id":"4121873783","tags":"addr:street:Avenida Carlos Gomes,amenity:post_office","lat":-30.0307795,"lng":-51.1806751},{"id":"4134017479","name":"Panvel","tags":"amenity:pharmacy,brand:Panvel,brand:wikidata:Q10344254,brand:wikipedia:pt:Panvel,healthcare:pharmacy","lat":-30.0182497,"lng":-51.1740443},{"id":"4151914591","name":"Snoopy Bar","tags":"amenity:bar","lat":-30.0427464,"lng":-51.1907066},{"id":"4151917089","name":"Caverna do Ratão","tags":"amenity:bar,website:http://www.cavernadoratao.com.br","lat":-30.0420176,"lng":-51.1915299},{"id":"4153333569","tags":"addr:housenumber:675,addr:street:Rua Eudoro Berlink,amenity:post_office","lat":-30.0243459,"lng":-51.1908351},{"id":"4312048990","name":"Panvel","tags":"amenity:pharmacy,brand:Panvel,brand:wikidata:Q10344254,brand:wikipedia:pt:Panvel,healthcare:pharmacy,wheelchair:yes","lat":-30.0368188,"lng":-51.1864512},{"id":"4331348397","name":"Casinha de Cachorro","tags":"addr:housenumber:412,addr:street:Avenida Nova York,amenity:restaurant,cuisine:hot_dog,delivery:yes","lat":-30.0184241,"lng":-51.1954445},{"id":"4431805337","name":"Agência Vila Jardim","tags":"amenity:post_office,operator:Correios,operator:wikidata:Q3375004,operator:wikipedia:en:Correios,wheelchair:yes","lat":-30.0408311,"lng":-51.1542917},{"id":"4450687816","name":"Farmais Paineira","tags":"amenity:pharmacy,dispensing:no,healthcare:pharmacy,opening_hours:Mo-Su 08:00-23:00,phone:+55 51 3338-2320,website:http://www.farmais.com.br/","lat":-30.0402769,"lng":-51.163998},{"id":"4508825428","name":"Cachorro do Bigode","tags":"amenity:restaurant,cuisine:hot_dog,takeaway:yes","lat":-30.0173889,"lng":-51.1525803},{"id":"4732283866","name":"ampm","tags":"brand:ampm,brand:wikidata:Q306960,brand:wikipedia:en:Ampm,shop:convenience,wheelchair:yes","lat":-30.0223591,"lng":-51.1847856},{"id":"4732283867","name":"ampm","tags":"brand:ampm,brand:wikidata:Q306960,brand:wikipedia:en:Ampm,shop:convenience","lat":-30.0284104,"lng":-51.1638163},{"id":"4732283871","name":"Panvel","tags":"amenity:pharmacy,brand:Panvel,brand:wikidata:Q10344254,brand:wikipedia:pt:Panvel,drive_through:no,healthcare:pharmacy,wheelchair:yes","lat":-30.0222513,"lng":-51.1848606},{"id":"4772964221","name":"Caixa Econômica Federal","tags":"addr:street:Avenida Carlos Gomes,amenity:bank,atm:yes,brand:Caixa Econômica Federal,brand:wikidata:Q835283,brand:wikipedia:pt:Caixa Econômica Federal","lat":-30.0278561,"lng":-51.181281},{"id":"4777755649","name":"Gecepel","tags":"addr:city:Porto Alegre,addr:housenumber:520,addr:street:Rua Guilherme Alves,addr:suburb:Petrópolis,email:loja03@gecepel.com.br,phone:+55 51 3354-6699,shop:supermarket","lat":-30.0520141,"lng":-51.1861566},{"id":"4825493126","name":"Massas do Forte","tags":"amenity:restaurant","lat":-30.0264557,"lng":-51.1864301},{"id":"4846502441","name":"Vê","tags":"addr:city:Porto Alegre,addr:housenumber:1265,addr:street:Avenida Lajeado,addr:suburb:Petrópolis,amenity:restaurant,cuisine:regional,diet:gluten_free:yes,diet:vegan:only,email:meteacolher@verestaurante.com.br,official_name:Vê Empório e Restaurante Vegano,opening_hours:Su-Sa 11:30-14:30,organic:yes,phone:+55 51 3022-4942,website:http://www.verestaurante.com.br/","lat":-30.034902,"lng":-51.1792865},{"id":"4894184418","name":"La Rouge Bistrô","tags":"addr:city:Porto Alegre,addr:housenumber:1587,addr:street:Avenida Mariland,amenity:restaurant,cuisine:mediterranean,diet:vegan:only,opening_hours:Tu-We 12:00-15:00; Th 12:00-15:00,19:30-22:30; Fr 12:00-15:00; Sa-Su 12:00-16:00,phone:+55 51 3019-7638,website:http://www.larougebistro.com.br/","lat":-30.0291264,"lng":-51.1930632},{"id":"4917687821","name":"Galeteria Sbardelotto","tags":"addr:housenumber:1669,addr:postcode:90520-002,addr:street:Avenida Plínio Brasil Milano,amenity:restaurant,cuisine:italian,description:Restaurante informal voltado ao galeto com acompanhamentos e massas artesanais com buffet de sobremesas.,opening_hours:Tu-Fr 11:30-14:00, 19:00-23:00; Sa 11:30-15:00, 19:00-23:00; Su 11:30-15:00,phone:+55 51 3328-7080,website:http://www.galeteriasbardelotto.com.br","lat":-30.0185129,"lng":-51.1749309},{"id":"4927018521","name":"Pizza Hut","tags":"amenity:restaurant,brand:Pizza Hut,brand:wikidata:Q191615,brand:wikipedia:en:Pizza Hut,cuisine:pizza","lat":-30.0294387,"lng":-51.1870177},{"id":"5014394168","name":"CT Bela Vista","tags":"addr:city:Porto Alegre,addr:housenumber:226,addr:postcode:90450-040,addr:street:Rua Jaraguá,leisure:fitness_centre,website:http://www.ctbelavista.com.br/","lat":-30.0366307,"lng":-51.1908293},{"id":"5022993844","name":"Dia","tags":"brand:Dia,brand:wikidata:Q925132,brand:wikipedia:es:Supermercados DIA,shop:supermarket","lat":-30.0243299,"lng":-51.1905377},{"id":"5023006341","name":"Ser Bixo","tags":"shop:pet","lat":-30.0171391,"lng":-51.1710817},{"id":"5023006482","name":"Salão 1475","tags":"shop:beauty","lat":-30.0192663,"lng":-51.1769922},{"id":"5023006493","name":"Plínio Mall","tags":"shop:mall","lat":-30.0183871,"lng":-51.1743224},{"id":"5023010054","name":"Bar da Tati","tags":"amenity:bar","lat":-30.0154598,"lng":-51.1625657},{"id":"5043652182","name":"Panvel","tags":"amenity:pharmacy,brand:Panvel,brand:wikidata:Q10344254,brand:wikipedia:pt:Panvel,healthcare:pharmacy","lat":-30.0436882,"lng":-51.187723},{"id":"5043658281","name":"Caixa Econômica Federal","tags":"amenity:bank,brand:Caixa Econômica Federal,brand:wikidata:Q835283,brand:wikipedia:pt:Caixa Econômica Federal","lat":-30.0436375,"lng":-51.1832687},{"id":"5230884924","name":"Ophtalmed","tags":"addr:housenumber:285 sala3,addr:street:Rua Engenheiro Walter Boehl,amenity:pharmacy,full_name:Ophtalmed Farmácia Oftalmológica,healthcare:pharmacy,opening_hours:Mo-Sa 08:00-21:00; Su 10:00-21:00,phone:+55 51 3340-3012","lat":-30.0223386,"lng":-51.1540005},{"id":"5291960992","name":"Roister","tags":"addr:city:Porto Alegre,addr:housenumber:1454,addr:postcode:90510-001,addr:street:Rua 24 de Outubro,addr:suburb:Auxiliadora,amenity:restaurant,description:Restaurante e bar com área lounge em espaço despojado serve menu sofisticado de lanches e pratos autorais.,opening_hours:Mo-Fr 11:30-14:00, 18:00-23:00; Sa 12:00-00:00","lat":-30.0220601,"lng":-51.1948305},{"id":"5296220663","name":"Love It","tags":"addr:housenumber:884,addr:street:Avenida Mariland,amenity:cafe,operator:Tu-Sa 09:00-20:00; Su 10:00-15:00,phone:+55 51 3094-6184","lat":-30.0225237,"lng":-51.1933951},{"id":"5921484981","name":"Asun Supermercados","tags":"shop:supermarket","lat":-30.019038,"lng":-51.1754265},{"id":"5929230840","name":"Delitzzi","tags":"addr:housename:Loja 64,addr:housenumber:6690,addr:street:Avenida Ipiranga,amenity:restaurant,diet:vegan:yes","lat":-30.0557992,"lng":-51.1756013},{"id":"5965150119","name":"MOOD To Go","tags":"addr:housenumber:25,addr:street:Rua Azevedo Sodré,amenity:restaurant,contact:facebook:https://www.facebook.com/Moodcafeteria/,contact:phone:+55 51 3019-4873,diet:gluten_free:only,diet:lactose_free:only,diet:vegan:yes,diet:vegetarian:yes,opening_hours:Mo-Sa 12:00-19:00,takeaway:yes","lat":-30.0174111,"lng":-51.171068},{"id":"6085960678","name":"Pizzaria Oca de Savóia - Delivery","tags":"addr:city:Porto Alegre,addr:street:Avenida Protásio Alves,amenity:restaurant,capacity:10,cuisine:pizza,delivery:yes,outdoor_seating:no,takeaway:yes","lat":-30.0437023,"lng":-51.1836874},{"id":"6111097974","name":"Carnitas","tags":"addr:city:Porto Alegre,addr:housenumber:908,addr:postcode:90440-190,addr:street:Avenida Mariland,addr:suburb:Auxiliadora,amenity:restaurant,capacity:40,cuisine:regional;international;burger,delivery:yes,opening_hours:Mo-Sa 11:30-20:00,takeaway:yes","lat":-30.0227393,"lng":-51.1936193},{"id":"6142971163","name":"PPKB","tags":"amenity:restaurant","lat":-30.0274631,"lng":-51.1809426},{"id":"6166925249","name":"The Chefs Hamburgeria","tags":"addr:housenumber:400,addr:street:Avenida Carlos Gomes,amenity:restaurant,cuisine:burger,wheelchair:yes","lat":-30.02527,"lng":-51.1825611},{"id":"6166925250","name":"Seasons","tags":"addr:housenumber:400,addr:street:Avenida Carlos Gomes,amenity:restaurant,cuisine:international,phone:+55 51 3508-7781,website:http://www.restauranteseasons.com.br,wheelchair:yes","lat":-30.0252418,"lng":-51.1825741},{"id":"6239844498","name":"Estética Lu","tags":"addr:street:R. Gen. Couto de Magalhães, 1935 - Higienópolis, Porto Alegre - RS, 90540-130,opening_hours:Tu-Sa 10:00-19:00,phone:+55 51 3325-6946,shop:beauty","lat":-30.0147476,"lng":-51.1820374},{"id":"6243171983","name":"Casa Vecchia Ristorante","tags":"addr:city:Porto Alegre,addr:housenumber:176,addr:postcode:90540-120,addr:street:Rua Auxiliadora,amenity:restaurant,cuisine:italian,description:A cozinha italiana tradicional de massas e carnes em pratos clássicos, com ambiente aconchegante e familiar..,opening_hours:Tu-Sa 11:30-23:30; Su 11:00-15:30,phone:+55 51 3342-1004","lat":-30.0207844,"lng":-51.1909561},{"id":"6243233204","name":"Bella Morano Pizzaria","tags":"addr:housenumber:23,addr:street:Avenida Coronel Lucas Oliveira, 23 - Auxiliadora, Porto Alegre - RS, 90440-01,amenity:restaurant,description:Cantina especializa em pizzas especiais servidas em ambiente elegantemente rústico de cabana aconchegante.Preço médio por pessoa: 50 reais,opening_hours:Tu-Su 19:00-23:00; Mo 09:00-17:00,payment:cryptocurrencies:Visa, Mastercard,phone:+55 51 3333-9899,website:http://www.bellamorano.com.br","lat":-30.0228233,"lng":-51.1954918},{"id":"6245712287","name":"Balcone Pizza Napolitana Boa Vista","tags":"addr:street:R. Anita Garibaldi, 2169 - Boa Vista, Porto Alegre - RS, 90480-201,amenity:restaurant,description:FAIXA DE PREÇO: R$ 19 - R$ 30 COZINHAS: Italiana, Pizza,opening_hours:Tu-Sa 11:30-15:00, 17:00-22:30,phone:+55 51 3069-8451,website:https://www.instagram.com/balconepizza/","lat":-30.0225029,"lng":-51.1742249},{"id":"6246537648","name":"Excalibur Forneria & Lounge","tags":"addr:city:Porto Alegre,addr:housenumber:238,addr:postcode:91330-020,addr:street:Rua Desembargador Espiridião Lima Medeiros,amenity:restaurant,cuisine:pizza,description:A gastronomia de pizzas tradicionais e especiais, com vinhos finos, em ambiente no estilo de castelo medieval.,internet_access:yes,opening_hours:Mo-We 11:30-14:30,19:00-23:00, Fr-Sa 19:00-23:00,phone:+55 51 3332-0404,website:excaliburforneria.com.br,wheelchair:yes","lat":-30.029048,"lng":-51.1685544},{"id":"6246537649","name":"Fornellone Ristorante","tags":"addr:city:Porto Alegre,addr:housenumber:93,addr:postcode:90550-070,addr:street:Avenida Nova York,addr:suburb:Auxiliadora,amenity:restaurant,cuisine:pizza;Italiana;$$_-_$$$;european,delivery:yes,description:Culinária descontraída em ambiente aconchegante com menu variado de carnes, massas e pizzas salgadas e doces.,opening_hours:Mo-Su 19:00-00:00,phone:+55 51 3028-7575,website:http://www.fornellone.com.br,wheelchair:limited","lat":-30.0214556,"lng":-51.1948308},{"id":"6246537650","name":"Restaurante Bene Naturale","tags":"addr:city:Porto Alegre,addr:housenumber:79,addr:postcode:90550-000,addr:street:Avenida Nova York,addr:suburb:Auxiliadora,amenity:restaurant,cuisine:Buffet;$,description:Buffet à vontade, aconchegante, casual Opções vegetarianas,diet:vegetarian:yes,opening_hours:Mo-Sa 11:00-15:00,phone:+55 51 3085-1222,wheelchair:yes","lat":-30.0215385,"lng":-51.1947795},{"id":"6250171956","name":"Sette Pastabar","tags":"addr:street:R. Auxiliadora, 248 - Auxiliadora, Porto Alegre - RS, 90540-130,amenity:restaurant,description:Focado em massas, a casa em nada se parece com uma tradicional cantina italiana. Os ambientes são amplos e cozinha é aberta,. A amatriciana é um dos pratos favoritos: rigatoni ao molho de tomate, com pancetta da casa, pimenta calabresa e pecorino romano.,opening_hours:Tu-Sa 19:00-23:00; Su 12:00-15:00,phone:+55 51 3012-2926","lat":-30.0214157,"lng":-51.1909065},{"id":"6250178691","name":"ROCK'S RESTAURANTE","tags":"amenity:restaurant,description:Gastrobar tradicional e intimista serve o menu alemão de filés altos grelhados em panelas de ferro e opções.O Jaeger Schnitzel (lombo suíno grelhado com molho madeira, nata e champignon, acompanhado d Späetzel) é um dos  pratos favoritos,opening_hours:Mo-Sa 17:30-23:30,phone:+55 51 3085-0203,website:https://www.restauranterocks.com.br/","lat":-30.0215244,"lng":-51.1920395},{"id":"6250183918","name":"Tartare Restaurante","tags":"addr:street:Av. Mariland, 696 - São João, Porto Alegre - RS, 90440-190,amenity:restaurant,description:Ideal para ir a dois, com a família, amigos ou sozinho, Recomendamos o filé à Portuguesa, servido com cebola, ovos, azeitonas pretas, pimentão vermelho e arroz.,opening_hours:Mo-Fr 18:00-00:00; Sa 12:00-15:00, 18:00-00:00; Su 12:00-15:00,phone:+55 51 3026-3888","lat":-30.0208111,"lng":-51.1937752},{"id":"6258895739","name":"Ciao Pizzeria Napoletana","tags":"addr:street:R. Anita Garibaldi, 694 - Loja 7 - Mont'Serrat, Porto Alegre - RS, 90450-000,amenity:restaurant,description:Cantina boêmia tem mesas ao ar livre e serve pizzas da casa de ingredientes especiais, com bordas recheadas.,opening_hours:Tu-Sa 11:30-15:00, 18:00-23:00; Su 18:00-23:00,phone:+55 51 3094-6767","lat":-30.0264568,"lng":-51.188858},{"id":"6258945071","name":"Restaurante You Yi","tags":"addr:street:R. Cândido Silveira, 242 - Auxiliadora, Porto Alegre - RS, 90540-010,amenity:restaurant,description:A casa chinesa é autêntica até na decoração. Os molhos de pimenta, gengibre e agridoce dispostos nas latinhas são uma assinatura. A Meia Lua é uma entrada para repetir sempre, e o Pato Laqueado é uma bagunça maravilhosa para comer com as mãos.,opening_hours:Mo-Su 12:00-14:00, 19:00-23:00,phone:+55 51 3342-3828,website:http://www.youyi.com.br/","lat":-30.0214615,"lng":-51.1920204},{"id":"6258962797","name":"Prinz","tags":"addr:street:R. Dom Pedro II, 1469 - São João, Porto Alegre - RS, 90550-143,amenity:restaurant,description:O filé ao molho de nata e a salada de batatas resumem o Prinz: alemão, tradicional e sem frescuras. Acredite no quão forte é a mostarda e vá com calma.,opening_hours:Mo-Sa 18:00-23:00,phone:+55 51 3383-0675","lat":-30.0200577,"lng":-51.1865463},{"id":"6258973165","name":"Brizza Forneria","tags":"addr:street:R. 24 de Outubro, 1409 - Independência, Porto Alegre - RS, 90510-002,amenity:restaurant,description:Apesar de as pizzas seguirem a tradicional receita italiana e serem feitas no forno a lenha, com massa de fermentação natural, os sabores são bem autênticos e inusitados. Prove a Sgt. Pepperoni, que utiliza creme de moranga no lugar do molho de tomate.,opening_hours:Mo-Fr 18:00-22:30, 09:00-18:00; Sa 11:30-22:30,phone:+55 51 3573-5539,website:https://m.facebook.com/brizzaforneria/","lat":-30.0223675,"lng":-51.1945839},{"id":"6258979253","name":"Bianca Pizzaria","tags":"addr:street:Av. Plínio Brasil Milano, 1817 - Higienópolis, Porto Alegre - RS, 90520-001,amenity:restaurant,description:Depois de 34 anos, a Bianca reformulou o formato de negócio e, desde junho, atende somente na modalidade de tele-entrega e retirada no local. É uma das clássicas de Porto Alegre.,opening_hours:Mo-Su 18:30-23:30,phone:+55 51 3328-5644","lat":-30.0180588,"lng":-51.1735115},{"id":"6258989128","name":"Pot. Pourri Pizzaria","tags":"addr:street:R. Pedro Chaves Barcelos, 845 - Bela Vista, Porto Alegre - RS, 90450-010,amenity:restaurant,description:O lugar é charmoso e ideal para ir a dois e curtir algo mais romântico. Entre as pizzas, destacamos a de cogumelos.,opening_hours:Tu-Su 19:00-23:30,phone:+55 51 3516-3960","lat":-30.0294399,"lng":-51.1851959},{"id":"6259027785","name":"Haus Burger Bar","tags":"addr:street:R. Dr. Prudente de Morães, 555 - Três Figueiras, Porto Alegre - RS, 91330-050,amenity:restaurant,description:Hamburgueria gourmet com opções saudáveis, fartas e criativas em ambiente luxuoso e aconchegante.,opening_hours:Mo-Sa 11:45-14:30, 18:00-23:30,phone:+55 51 3407-2367","lat":-30.0293484,"lng":-51.1654739},{"id":"6259943640","name":"Tartoni Ristorante","tags":"addr:street:Av. Túlio de Rose, 80 - 70 - Passo d'Areia, Porto Alegre - RS, 91340-110,amenity:restaurant,description:Chef inovadora de receitas gourmets da cozinha italiana com influência mediterrânea, ambiente contemporâneo.,internet_access:yes,opening_hours:Mo-Su 11:30-23:30,phone:+55 51 3345-2881,website:http://tartoni.com.br/","lat":-30.0219439,"lng":-51.1629482},{"id":"6340524615","name":"Panvel","tags":"addr:housenumber:2099,addr:postcode:90480-201,addr:street:Rua Anita Garibaldi,amenity:pharmacy,brand:Panvel,brand:wikidata:Q10344254,brand:wikipedia:pt:Panvel,dispensing:yes,healthcare:pharmacy,phone:+55 51 3328-1410","lat":-30.0226258,"lng":-51.174505},{"id":"6385584536","name":"Dom Carvalho","tags":"amenity:restaurant","lat":-30.0557424,"lng":-51.1899104},{"id":"6385617257","name":"Villaggio","tags":"amenity:restaurant,cuisine:italian,wheelchair:yes","lat":-30.0550756,"lng":-51.1865318},{"id":"6385617258","name":"Usina das Massas","tags":"amenity:restaurant,cuisine:italian,wheelchair:yes","lat":-30.0550315,"lng":-51.1864218},{"id":"6385617259","name":"Jefe Grill","tags":"amenity:restaurant","lat":-30.0550153,"lng":-51.1863011},{"id":"6424601026","name":"Porto 466 Café e Restaurante","tags":"amenity:restaurant,contact:email:atendimentoporto466@gmail.com,opening_hours:Mo-Th 07:30-17:30; Fr 07:30-16:30","lat":-30.0258827,"lng":-51.1821109},{"id":"6602932093","name":"Bar e Restaurante Petrópolis","tags":"addr:city:Porto Alegre,addr:housenumber:2194,addr:street:Avenida Protásio Alves,addr:suburb:Petrópolis,amenity:restaurant","lat":-30.0434143,"lng":-51.1873257},{"id":"7118336764","name":"Zaffari","tags":"addr:street:Avenida Plínio Brasil Milano,amenity:restaurant","lat":-30.0198641,"lng":-51.1808633},{"id":"7171847157","name":"Sicredi","tags":"amenity:bank,atm:yes,brand:Sicredi,brand:wikidata:Q3483060,brand:wikipedia:pt:Sistema de Crédito Cooperativo,drive_through:no","lat":-30.0239991,"lng":-51.1837992},{"id":"7171847158","tags":"amenity:atm,cash_in:yes,currency:BRL:yes,drive_through:no,network:Saque e Pague,operator:Saque e Pague","lat":-30.0240085,"lng":-51.1837853},{"id":"7171847159","tags":"amenity:atm,cash_in:yes,check_date:2022-04-30,currency:BRL:yes,drive_through:no,network:Saque e Pague,operator:Saque e Pague","lat":-30.0162467,"lng":-51.186243},{"id":"7214924073","name":"Mark Hamburgueria","tags":"addr:housenumber:909,addr:street:Av. Mariland, 908 - Auxiliadora, Porto Alegre - RS, 90440-190,amenity:restaurant,opening_hours:Mo-Sa 11:30-15:00, 18:30-23:30,phone:+55 51 3519-6638","lat":-30.022768,"lng":-51.1936684},{"id":"7214956136","name":"Pane di Nanne","tags":"addr:housenumber:1566,addr:street:R. 24 de Outubro, 1566 - Auxiliadora, Porto Alegre - RS, 90510-001,craft:bakery,opening_hours:Mo-Fr 08:00-19:00; Sa 08:00-18:00,phone:+55 51 3207-8607","lat":-30.02178,"lng":-51.1932106},{"id":"7214990366","name":"Los Cinco Parrillaria","tags":"addr:housenumber:62,addr:street:Av. Nova York, 62 - Auxiliadora, Porto Alegre - RS, 90550-070,amenity:restaurant,description:Gastrobar convidativo com área externa tem grelhados robustos à moda uruguaia, com vinhos e cervejas seletas.,opening_hours:Su 11:30-16:00; Tu-Fr 18:00-23:30; Sa 11:30-15:00, 19:00-23:30,phone:+55 51 3392-8055","lat":-30.0216408,"lng":-51.1951637},{"id":"7214997077","name":"Restaurante Bene Naturale","tags":"addr:housenumber:79,addr:street:Av. Nova York, 79 - Auxiliadora, Porto Alegre - RS, 90550-000,amenity:restaurant,opening_hours:Mo-Sa 11:00-15:00,phone:+55 51 3085-1222","lat":-30.0214481,"lng":-51.194809},{"id":"7216086827","name":"A Cantina do Press","tags":"addr:housenumber:1800,addr:street:Av. João Wallig, 1800 - loja 2264 - Passo d'Areia, Porto Alegre - RS, 91349-900,amenity:restaurant,description:\\Em um super local do Shopping Iguatemi, o mais novo restaurante do Grupo Press Gastronomia e Diversão. A Cantina do Press inaugurou em outubro de 2019 e traz a POA o que tem de mais legal na cozinha e na coquetelaria italiana.\\,opening_hours:Su 12:00-22:00; Mo-Fr 12:00-15:00, 18:30-23:30,phone:+55 51 3029-0019,website:http://www.grupopress.com.br/","lat":-30.0251217,"lng":-51.1624184},{"id":"7217213488","name":"Restaurante Sevilla Garden","tags":"addr:housenumber:1344,addr:street:R. 24 de Outubro, 1344 - Independência, Porto Alegre - RS, 90510-001,amenity:restaurant,opening_hours:Mo-Fr 11:00-14:30; Sa 11:30-14:45,phone:+55 51 99263-4682","lat":-30.0223103,"lng":-51.1953697},{"id":"8867409917","name":"Fazenda barbanegra","tags":"addr:housenumber:3228,addr:street:Avenida Doutor Nilo Peçanha,amenity:restaurant","lat":-30.0284168,"lng":-51.1580886},{"id":"9014388240","name":"Saque e Pague","tags":"amenity:atm,cash_in:yes,currency:BRL:yes,drive_through:no,layer:-1,operator:Saque e Pague","lat":-30.0202437,"lng":-51.1804892},{"id":"9883301795","name":"Oakberry Iguatemi","tags":"addr:city:Porto Alegre/RS,addr:housenumber:1800,addr:postcode:91349-900,addr:street:Avenida João Wallig,addr:suburb:Passo d'Areia,amenity:restaurant,cuisine:açaí,level:1","lat":-30.0251105,"lng":-51.1621197}]