[{"id":"4674739899","tags":"amenity:pharmacy,healthcare:pharmacy","lat":-22.3498398,"lng":-41.7992999},{"id":"6029761066","tags":"amenity:grave_yard","lat":-22.3545865,"lng":-41.8071386},{"id":"9579555612","name":"Polícia Federal do Brasil","tags":"addr:city:Macaé,addr:housenumber:230,addr:postcode:27947-280,addr:street:Rua Camilo Nogueiro da Gama,addr:suburb:Botafogo,amenity:police,operator:Polícia Federal do Brasil,operator:en:Federal Police of Brazil,operator:wikidata:Q2289697,operator:wikipedia:pt:Polícia Federal do Brasil,phone:+55 22 2796 8300","lat":-22.3635064,"lng":-41.7970236},{"id":"10641810374","name":"Supermercado Virgem Santa","tags":"addr:city:Macaé,addr:postcode:27948-000,addr:street:Estrada Virgem Santa,addr:suburb:Virgem Santa,opening_hours:Mo-Sa 08:00-21:00; Su 08:00-14:00,payment:cash:yes,payment:credit_cards:yes,payment:debit_cards:yes,payment:food_stamps:yes,payment:meal_voucher:yes,phone:02227652902,shop:supermarket,wheelchair:yes","lat":-22.3454555,"lng":-41.8011303}]