[{"id":"4816557421","name":"Escola Estadual João Rogelío Schuertz","tags":"amenity:school,name:en:School Estadual João Rogelío Schuertz,name:pt:Escola Estadual João Rogelío Schuertz,opening_hours:Mo-Fr 07:00-23:45","lat":1.8231559,"lng":-61.1287075},{"id":"4818270123","name":"Comercial Junior","tags":"name:en:Comercial Junior,name:pt:Comercial Junior,opening_hours:Mo-Fr 06:00-22:00,shop:supermarket","lat":1.8195481,"lng":-61.1365482},{"id":"5020884485","name":"Escola Municipal Idnéa Barbosa","tags":"amenity:school","lat":1.8211387,"lng":-61.1326915},{"id":"5022309633","name":"Universidade Estadual de Roraima","tags":"amenity:school,name:pt:Universidade Estadual de Roraima","lat":1.8272404,"lng":-61.1304072},{"id":"5024988521","name":"UNIVIRR","tags":"amenity:school,name:pt:UNIVIRR","lat":1.8270175,"lng":-61.130253},{"id":"5025005921","name":"Escola Municipal Manoel Pereira da Costa","tags":"amenity:school,name:pt:Escola Municipal Manoel Pereira da Costa","lat":1.8134116,"lng":-61.1344797},{"id":"5028468921","name":"Escola Estadual José Vieira Sales Guerra","tags":"amenity:school,name:pt:Escola Estadual José Vieira Sales Guerra","lat":1.8085156,"lng":-61.1345087},{"id":"5030188021","name":"Guarda Civil Municipal","tags":"amenity:police,name:pt:Guarda Civil Municipal","lat":1.8128969,"lng":-61.1283057}]