[{"id":"1661701594","name":"DaDo Pub (FECHADO)","tags":"addr:street:R. Fernando Gomes, 80 - Moinhos de Vento, Porto Alegre - RS, 90510-010,amenity:restaurant,description:Buffet e cardápio internacional, além de cervejas artesanais da marca DaDo Bier, em casa de estilo europeu.,opening_hours:Mo-Fr 11:30-14:30,17:00-00:00, Sa 12:00-00:00 ,Su 12:00-15:30,phone:+55 51 3395-1468,website:https://www.dadobier.com.br/","lat":-30.0262447,"lng":-51.2051315},{"id":"1669235414","name":"Bazkaria","tags":"addr:street:R. Comendador Caminha, 324 - Moinhos de Vento, Porto Alegre - RS, 90430-030,amenity:restaurant,cuisine:basque,description:É uma pizzaria bem tradicional da cidade. Adoramos a Paixão Côrtes, com picanha defumada, muçarela de búfala, rúcula e tomate-cereja.,opening_hours:Mo-Su 18:00-00:00,phone:+55 51 3061-6262,website:https://www.bazkaria.com.br,wheelchair:yes","lat":-30.0260464,"lng":-51.201157},{"id":"2104660149","name":"Vilaró","tags":"amenity:restaurant,cuisine:steak_house,wheelchair:yes","lat":-30.0265689,"lng":-51.204875},{"id":"2104660150","tags":"shop:supermarket","lat":-30.0295806,"lng":-51.2056415},{"id":"2136838231","name":"Panvel","tags":"addr:housenumber:20,addr:street:Avenida Goethe,addr:unit:101,amenity:pharmacy,brand:Panvel,brand:wikidata:Q10344254,brand:wikipedia:pt:Panvel,healthcare:pharmacy,phone:+55 51 3332-1582,website:https://www.panvel.com/,wheelchair:yes","lat":-30.029735,"lng":-51.2010722},{"id":"2154976309","name":"Bar do Goethe","tags":"addr:housenumber:112,addr:postcode:90510-000,addr:street:Rua 24 de Outubro,amenity:bar,email:bardogoethe@gmail.com,internet_access:wlan,opening_hours:Mo-Th 14:00-22:00; Fr-Sa 9:00-22:00,phone:+55 51 2118-7818,start_date:1987,website:http://www.bardogoethe.com.br","lat":-30.0278462,"lng":-51.2064139},{"id":"2271267022","tags":"leisure:sports_centre,sport:multi,wheelchair:limited","lat":-30.0270944,"lng":-51.2015776},{"id":"2446623716","name":"Galeria de Arte do DMAE","tags":"addr:housenumber:200,addr:postcode:90510-000,addr:street:Rua 24 de Outubro,amenity:arts_centre,layer:-1,loc_name:Galeria do DMAE,opening_hours:Mo-Fr 08:00-17:30,tourism:museum,website:http://dmaegaleriadearte.blogspot.com.br/","lat":-30.0271567,"lng":-51.2057402},{"id":"2597547217","name":"Farmais","tags":"amenity:pharmacy,healthcare:pharmacy","lat":-30.0304516,"lng":-51.2017848},{"id":"3388275987","name":"Koh Pee Pee","tags":"addr:housenumber:83,addr:postcode:90430-150,addr:street:Rua Schiller,amenity:restaurant,cuisine:thai,operator:The best restaurant in town some people claim. Very good spicy and \ngreat service. Decent wine list, very nice interior and great setting. \nGood value for money.,phone:+55 51 3333-5150,website:http://kohpeepee.com.br","lat":-30.0309601,"lng":-51.2016062},{"id":"3735357470","name":"Peppo Cucina","tags":"addr:city:Porto Alegre,addr:housenumber:161,addr:postcode:90430-091,addr:street:Rua Dona Laura,addr:suburb:Rio Branco,amenity:restaurant,cuisine:italian,wheelchair:no","lat":-30.0297744,"lng":-51.2041102},{"id":"3839067837","name":"Lorita","tags":"addr:housenumber:678,addr:postcode:90430-131,addr:street:Rua Castro Alves,amenity:restaurant,phone:+55 51 3264-6000,wheelchair:limited","lat":-30.0309629,"lng":-51.2037331},{"id":"3839067838","name":"Sushi Drive","tags":"addr:housenumber:140,addr:postcode:90430-100,addr:street:Avenida Goethe,amenity:restaurant,cuisine:sushi,phone:+55 51 3335-3333,website:https://www.sushidrive.com.br/,wheelchair:yes","lat":-30.0306205,"lng":-51.2019596},{"id":"3839067839","name":"Sashiburi","tags":"addr:housenumber:307,addr:postcode:90430-091,addr:street:Rua Dona Laura,amenity:restaurant,cuisine:sushi,phone:+55 51 3028-5667,website:http://www.sashiburi.com.br/","lat":-30.0297373,"lng":-51.2039604},{"id":"3839067841","tags":"addr:street:Rua Schiller,amenity:post_office,wheelchair:yes","lat":-30.0302711,"lng":-51.2015017},{"id":"4463529055","name":"Petrolli's Grill","tags":"addr:housenumber:41,addr:street:Rua Tenente Coronel Fabricio Pilar,amenity:restaurant,phone:+55 51 3331-2538","lat":-30.0263738,"lng":-51.1971156},{"id":"4463529057","name":"Panelinha","tags":"addr:street:Rua Dona Laura,amenity:restaurant","lat":-30.0292413,"lng":-51.1987763},{"id":"4675711830","name":"Marquêz","tags":"addr:street:Rua Comendador Caminha,amenity:restaurant,cuisine:international","lat":-30.0281201,"lng":-51.2021431},{"id":"4675711832","tags":"amenity:cafe","lat":-30.0291495,"lng":-51.2011457},{"id":"4895392128","name":"Fit Academia","tags":"addr:housenumber:64,addr:street:Rua Doutor Florêncio Ygartua,email:contato@fitacademia.esp.br,leisure:sports_centre,opening_hours:Mo-Fr 06:30-22:00; Sa 09:00-15:00,phone:+55 51 3264-1111,sport:multi,website:https://www.fitacademia.esp.br/","lat":-30.0270769,"lng":-51.2030291},{"id":"5020375066","name":"Minds English School","tags":"amenity:school","lat":-30.0257345,"lng":-51.2020779},{"id":"5020381215","name":"Caixa Econômica Federal","tags":"addr:city:Porto Alegre,addr:street:Rua 24 de Outubro,addr:suburb:Moinhos de Vento,amenity:bank,atm:yes,brand:Caixa Econômica Federal,brand:wikidata:Q835283,brand:wikipedia:pt:Caixa Econômica Federal,drive_through:no,operator:Caixa Econômica Federal","lat":-30.0261992,"lng":-51.2024761},{"id":"5020381419","name":"QoD Barber Shop","tags":"addr:city:Porto Alegre,addr:street:Rua 24 de Outubro,addr:suburb:Moinhos de Vento,shop:beauty","lat":-30.0259639,"lng":-51.2027833},{"id":"5020383931","name":"Banco Santander","tags":"addr:street:Rua 24 de Outubro,amenity:bank,brand:Banco Santander,brand:en:Santander Bank,brand:es:Banco Santander,brand:wikidata:Q6496310,brand:wikipedia:es:Banco Santander,name:en:Santander Bank,name:es:Banco Santander,official_name:Santander Group","lat":-30.0268264,"lng":-51.2039253},{"id":"5022058817","name":"Delícia Natural","tags":"addr:housenumber:70,addr:postcode:90430-010,addr:street:Rua Doutor Florêncio Ygartua,amenity:restaurant,phone:+55 51 3237-3488","lat":-30.0271941,"lng":-51.2029621},{"id":"5043343920","name":"051 Burguer","tags":"addr:city:Porto Alegre,addr:housenumber:93,addr:postcode:90450-040,addr:street:Rua Tenente Coronel Fabricio Pilar,amenity:restaurant,cuisine:burger,delivery:yes,outdoor_seating:yes,phone:+55 51 3377-3680","lat":-30.0263062,"lng":-51.1964713},{"id":"5431413773","tags":"shop:pet","lat":-30.0287985,"lng":-51.2000779},{"id":"5431413777","tags":"leisure:fitness_centre","lat":-30.0292291,"lng":-51.1986559},{"id":"5865548456","name":"Estômago Café Vegano","tags":"addr:city:Porto Alegre,addr:housenumber:275,addr:street:Rua Miguel Tostes,addr:suburb:Rio Branco,amenity:cafe,contact:facebook:https://www.facebook.com/estomagocafe/,cuisine:international,diet:vegan:only,email:estomagocafe@hotmail.com,opening_hours:Mo-Fr 12:00-20:00; Sa 12:00-18:00,phone:+55 51 3573-5396","lat":-30.0306083,"lng":-51.2059537},{"id":"5929230837","name":"Kaichili","tags":"addr:housenumber:375,addr:street:Rua Mostardeiro,amenity:restaurant,contact:facebook:https://www.facebook.com/KaichiliMexicanKitchen/,cuisine:mexican,delivery:yes,diet:vegan:yes,diet:vegetarian:yes,email:kaichili@kaichili.com.br,opening_hours:Mo-Sa 11:00-23:00; Su 11:00-22:00,phone:+55 51 3533-3903,takeaway:yes,website:https://www.kaichili.com.br/","lat":-30.028795,"lng":-51.2031964},{"id":"5965150126","name":"Modesta Vegana","tags":"addr:housenumber:275,addr:street:Rua Miguel Tostes,contact:facebook:https://www.facebook.com/modestavegana/,diet:vegan:only,level:2,phone:+55 51 98019-2717,shop:convenience","lat":-30.0306018,"lng":-51.2059606},{"id":"6243282670","name":"Constantino","tags":"addr:housenumber:44,addr:street:Fernando Gomes,amenity:restaurant,description:Restaurante aconchegante oferece área interna e externa, com muitas plantas, deck, drinques e comida variada.Faixa de preço:,opening_hours:Mo-Sa 12:00-00:00,phone:+55 51 3346-8589,website:http://constantinocafe.com.br","lat":-30.0259476,"lng":-51.20541},{"id":"6258893449","name":"Press Bar Restaurante","tags":"addr:street:R. Hilário Ribeiro, 281 - Moinhos de Vento, Porto Alegre - RS, 90510-040,amenity:restaurant,description:Gastronomia variada e destaque ao estrogonofe da casa, drinques, quintal arborizado em clima moderno e retrô.,opening_hours:Mo-Su 12:00-23:00,phone:+55 51 3222-7718","lat":-30.0259171,"lng":-51.2040062},{"id":"6259044170","name":"Per Tutti Galeto","tags":"amenity:restaurant,description:Comida ítalo-brasileira, como galetos assados, sopa de capeletti e massas, em casa aconchegante e tradicional.,opening_hours:Tu-Sa 11:00-23:00; Su 11:30-15:30,phone:+55 51 3330-4060","lat":-30.0293331,"lng":-51.200058},{"id":"6259964757","name":"House Café Bistro","tags":"addr:housenumber:19,addr:street:Rua Dona Laura, 19 - Rio Branco, Porto Alegre - RS, 90430-090,amenity:restaurant,cuisine:french,description:Bistrô requintado e aconchegante, com música ambiente e um extenso cardápio da culinária sofisticada francesa.,opening_hours:Mo-We 12:00-14:00; Th-Sa 20:00-24:00,phone:+55 51 3086-3087,website:https://www.housecafebistro.com.br/","lat":-30.0298106,"lng":-51.2054606},{"id":"6260014589","name":"20BARRA9 Carniceria Bar Porto Alegre","tags":"addr:street:R. Hilário Ribeiro, 287 - Moinhos de Vento, Porto Alegre - RS, 90510-040,amenity:restaurant,description:Hambúrgueres artesanais e espetos, além de brownies, cervejas e coquetéis, em espacinho boêmio e aconchegante.,opening_hours:Mo-Su 11:30-00:00,website:20barra9.com","lat":-30.0259317,"lng":-51.2039369},{"id":"6260040232","name":"Urban Farmcy","tags":"addr:postcode:90510-040,addr:street:R. Hilário Ribeiro, 299 - Moinhos de Vento, Porto Alegre - RS, 90510-040,amenity:restaurant,cuisine:Natural,description:Restaurante de alimentação natural, visa combinação de ingredientes de alto valor nutritivo e espaço simples.,opening_hours:Mo-Sa 11:30-23:30, Su 11:30-19:30,outdoor_seating:yes,phone:+55 51 99743-2769,website:https://www.urbanfarmcy.com.br/,wheelchair:yes","lat":-30.0259634,"lng":-51.2039308},{"id":"6584586979","name":"Ponto Chic","tags":"addr:street:Rua Mostardeiro,amenity:cafe,wheelchair:limited","lat":-30.0289209,"lng":-51.206002},{"id":"6584586980","tags":"addr:street:Rua 24 de Outubro,amenity:restaurant","lat":-30.0281081,"lng":-51.2057177},{"id":"6859016456","name":"Panvel","tags":"amenity:pharmacy,brand:Panvel,brand:wikidata:Q10344254,brand:wikipedia:pt:Panvel,dispensing:yes,healthcare:pharmacy,wheelchair:yes","lat":-30.0288161,"lng":-51.2041674},{"id":"6859016457","name":"Safra","tags":"amenity:bank","lat":-30.0283085,"lng":-51.2042512},{"id":"7231247196","name":"Serefe Cafè","tags":"addr:housenumber:5,addr:street:Av. Goethe, 5 - Rio Branco, Porto Alegre - RS, 90430-100,amenity:bar,opening_hours:Mo-Su 15:00-00:00","lat":-30.0288448,"lng":-51.2009277},{"id":"7231261232","name":"SushiGo","tags":"addr:housenumber:13,addr:street:Avenida Goethe 13 Goethe 13 - Moinhos de Vento, Porto Alegre - RS, 90430-100,amenity:restaurant,opening_hours:Mo-Su 11:15-14:30, 18:00-23:30,phone:+55 51 3022-2525,website:http://www.sushigopoa.com.br/","lat":-30.0290241,"lng":-51.2010536},{"id":"7231280654","name":"La Donne Coiffeur","tags":"addr:housenumber:292,addr:street:R. Dr. Florêncio Ygartua, 292 - 01 - Moinhos de Vento, Porto Alegre - RS, 90430-010,opening_hours:Mo-Fr 09:00-18:30; Sa 09:00-14:00,phone:+55 51 3279-2469,shop:beauty,website:http://ledonnecoiffeur.vitrinevirtual.net/","lat":-30.0290527,"lng":-51.20298},{"id":"7574999075","name":"Coffee & Stuff","tags":"amenity:cafe,website:https://www.coffeenstuffbrasil.com/","lat":-30.0265879,"lng":-51.2047564},{"id":"8825291065","name":"Mais1 Café - Porto Alegre","tags":"addr:city:Porto Alegre,addr:housenumber:435,addr:postcode:90510-002,addr:street:Rua 24 de Outubro,addr:suburb:Moinhos de Vento,amenity:cafe,cuisine:coffee_shop,website:https://www.mais1cafe.com.br","lat":-30.0269316,"lng":-51.2034326},{"id":"9223794960","name":"It's Time to Coffee","tags":"addr:city:Porto Alegre,addr:housenumber:16,addr:postcode:90430-150,addr:street:Rua Schiller,addr:suburb:Rio Branco,amenity:cafe,cuisine:coffee_shop,website:https://www.instagram.com/itstimetocoffee_/","lat":-30.0303401,"lng":-51.2015357}]