[{"id":"6513220729","name":"Minimercado Martins","tags":"shop:supermarket","lat":-29.9614382,"lng":-51.1993118},{"id":"6513220730","name":"Mini Mercado Triguingo","tags":"shop:supermarket","lat":-29.9615272,"lng":-51.2003334},{"id":"6513997296","name":"Armazém Avenida","tags":"shop:supermarket","lat":-29.9616538,"lng":-51.2008814},{"id":"6612275504","name":"Minimercado Castro","tags":"shop:supermarket","lat":-29.9621923,"lng":-51.200808},{"id":"6612275509","name":"Tempero Do Cheff","tags":"amenity:restaurant","lat":-29.9624043,"lng":-51.2006212}]