[{"id":"6188040699","name":"Grilleto","tags":"amenity:restaurant","lat":-21.7820737,"lng":-48.2010463},{"id":"6188040701","name":"Divino Fogão","tags":"amenity:restaurant","lat":-21.7819891,"lng":-48.2012072},{"id":"6188040704","name":"JINJIN","tags":"amenity:restaurant,cuisine:japanese","lat":-21.7822755,"lng":-48.2009953},{"id":"6221474642","name":"Rock & Ribs","tags":"amenity:restaurant","lat":-21.7829177,"lng":-48.2027079},{"id":"7120524342","name":"Espaço União Livraria e Café","tags":"shop:books","lat":-21.7824114,"lng":-48.2025836}]