[{"id":"3358279119","name":"Colégio Cenecista Dr. José Ferreira","tags":"amenity:school","lat":-19.7598196,"lng":-47.9327584},{"id":"3358298194","name":"Banco do Brasil","tags":"addr:city:Uberaba,addr:street:Rua Prudente de Morais,addr:suburb:Abadia,amenity:bank,atm:yes,brand:Banco do Brasil,brand:wikidata:Q610817","lat":-19.7601939,"lng":-47.9255509},{"id":"3358305923","name":"Caixa Econômica Federal","tags":"addr:city:Uberaba,addr:street:Rua Prudente de Morais,addr:suburb:Abadia,amenity:bank,atm:yes,brand:Caixa Econômica Federal,brand:wikidata:Q835283","lat":-19.7604308,"lng":-47.9256301},{"id":"3385395445","name":"Supermercado Batista","tags":"addr:street:Rua Prudente de Morais,shop:supermarket","lat":-19.7605675,"lng":-47.9248864},{"id":"5210598048","name":"Drogão Vida Uberaba","tags":"amenity:pharmacy,healthcare:pharmacy","lat":-19.7602398,"lng":-47.9262555},{"id":"5210598049","name":"Correios","tags":"amenity:post_office","lat":-19.7597402,"lng":-47.9285555},{"id":"5210872728","tags":"amenity:restaurant,cuisine:pizza","lat":-19.7590812,"lng":-47.9292155}]