[{"id":"820950742","name":"Prezunic","tags":"shop:supermarket","lat":-22.9214909,"lng":-43.1973702},{"id":"823949921","name":"Escola Municipal Guatemala","tags":"IPP:BAIRRO:Centro,IPP:CHAVE:11238,IPP:CODATIVIDA:0,IPP:CODBAIRRO:005,IPP:COD_INEP:33063141,IPP:COD_SMA:011238,IPP:CRE:01,IPP:DESIGNACAO:0102006,IPP:ENDNOVO:http://webapp.sme.rio.rj.gov.br/jcartela/publico/pesquisa.do?idSetor=11238&cmd=load,IPP:FLG_VALIDA:S,addr:housenumber:55,addr:street:Praça Presidente Aguirre Cerda,amenity:school,phone:+55-21-22217569","lat":-22.9181905,"lng":-43.1884086},{"id":"823949925","name":"Escola Municipal Estados Unidos","tags":"IPP:BAIRRO:Catumbi,IPP:CHAVE:10788,IPP:CODATIVIDA:0,IPP:CODBAIRRO:006,IPP:COD_INEP:33063133,IPP:COD_SMA:010788,IPP:CRE:01,IPP:DESIGNACAO:0103001,IPP:ENDNOVO:http://webapp.sme.rio.rj.gov.br/jcartela/publico/pesquisa.do?idSetor=10788&cmd=load,IPP:FLG_VALIDA:S,addr:housenumber:453,addr:street:Rua Itapiru,amenity:school,phone:+55-21-25021534","lat":-22.9215693,"lng":-43.1964129},{"id":"823950923","name":"Creche Municipal Brincadeiras de Criança","tags":"IPP:BAIRRO:Rio Comprido,IPP:CODATIVIDA:0,IPP:CODBAIRRO:007,IPP:COD_INEP:33238200,IPP:CRE:01,IPP:DESIGNACAO:0103605,IPP:ENDERECO:Rua Sebastião Rocha, s/n,IPP:ENDNOVO:http://webapp.sme.rio.rj.gov.br/jcartela/publico/pesquisa.do?idSetor= &cmd=load,amenity:school","lat":-22.9189417,"lng":-43.1980522},{"id":"1683220359","name":"Bar do Gomez (Armazém São Thiago)","tags":"amenity:bar,wheelchair:limited","lat":-22.9213004,"lng":-43.1894948},{"id":"4404781052","name":"Esqunia de Santa","tags":"amenity:bar,wheelchair:limited","lat":-22.9211757,"lng":-43.1893886},{"id":"4418226389","tags":"addr:housenumber:24,addr:street:Rua Áurea,amenity:restaurant,cuisine:brazilian;regional,email:negaterezabar@gmail.com,name:en:Nega Tereza Bar,name:pt:Nega Tereza Bar","lat":-22.921242,"lng":-43.1895625},{"id":"4419686889","tags":"shop:convenience","lat":-22.9209745,"lng":-43.1896311},{"id":"4421888890","tags":"amenity:restaurant,cuisine:pasta;pizza;sandwich,name:pt:Esquina de Santa","lat":-22.9212217,"lng":-43.1894141},{"id":"8114278925","name":"Bar Mama Shelter","tags":"addr:city:Rio de Janeiro,addr:housenumber:5,addr:street:Rua Paschoal Carlos Magno,addr:suburb:Santa Teresa,amenity:bar,website:https://www.mamashelter.com","lat":-22.9198299,"lng":-43.18816},{"id":"10060999466","name":"Agô - Bar de Encruza","tags":"amenity:bar","lat":-22.9214688,"lng":-43.1894291}]