[{"id":"4224680592","name":"Hospital de Emergência","tags":"addr:housenumber:800,addr:street:Avenida Marcílio Dias,amenity:hospital,emergency:yes,healthcare:hospital,healthcare:speciality:general,opening_hours:24/7,operator:Prefeitura","lat":-22.4629812,"lng":-44.460262},{"id":"4931543738","tags":"leisure:fitness_centre","lat":-22.4639341,"lng":-44.4586778},{"id":"5543577082","name":"Entrada 1 do parque das Águas","tags":"crossing:zebra,leisure:park,traffic_calming:table","lat":-22.462202,"lng":-44.4584325},{"id":"5543583033","name":"Estádio do Trabalhador","tags":"leisure:stadium,sport:soccer,wikidata:Q5402244","lat":-22.4640408,"lng":-44.4554508},{"id":"5554572175","tags":"amenity:parking","lat":-22.4625842,"lng":-44.4513862},{"id":"5569007593","name":"89  Delegacia de Polícia","tags":"amenity:police","lat":-22.4626084,"lng":-44.4570799},{"id":"9722097990","name":"Colegio Anglo Americano","tags":"addr:city:Resende,addr:housenumber:134,addr:postcode:27510-030,addr:street:Rua Pandia Calogeras,addr:suburb:Jardim Jaliscp,amenity:school,grades:1 to 13,religion:none,website:https://www.angloamericano.edu.br/resende/","lat":-22.4656635,"lng":-44.4529938}]