[{"id":"1411551146","name":"EPA","tags":"shop:supermarket","lat":-20.3656036,"lng":-40.3032226},{"id":"3482119999","name":"Kipizza","tags":"amenity:restaurant,contact:phone:+55 27 3340-2676,cuisine:pizza","lat":-20.363393,"lng":-40.2994691},{"id":"3855182958","name":"Gaúcho Gourmet","tags":"addr:city:Vila Velha,addr:housenumber:1702,addr:postcode:29102-385,addr:street:Avenida Santa Leopoldina,addr:suburb:Coqueiral de Itaparica,amenity:restaurant,contact:phone:(27) 3349-1805,cuisine:regional","lat":-20.3677806,"lng":-40.3045508},{"id":"3855191757","name":"Farmácia Pague Menos","tags":"addr:city:Vila Velha,addr:housenumber:125,addr:postcode:29102-385,addr:street:Avenida Santa Leopoldina,addr:suburb:Coqueiral de Itaparica,amenity:pharmacy,contact:phone:(27) 3349-1417","lat":-20.3665906,"lng":-40.3037796},{"id":"3855192857","name":"Farmácia Santa Lúcia","tags":"addr:city:Vila Velha,addr:housenumber:1825,addr:postcode:29102-040,addr:street:Avenida Santa Leopoldina,addr:suburb:Coqueiral de Itaparica,amenity:pharmacy,level:1","lat":-20.3660691,"lng":-40.3035533},{"id":"3855201933","name":"Farmácia Preço Baixo","tags":"addr:city:Vila Velha,addr:housenumber:1571,addr:postcode:29102-040,addr:street:Avenida Santa Leopoldina,addr:suburb:Coqueiral de Itaparica,amenity:pharmacy,level:1,website:https://www.farmaciasprecobaixo.com.br/","lat":-20.3653144,"lng":-40.3031502},{"id":"3855215288","name":"Agoracred Financeira","tags":"addr:city:Vila Velha,addr:housenumber:1440,addr:postcode:29102-200,addr:street:Avenida Santa Leopoldina,addr:suburb:Coqueiral de Itaparica,amenity:bank,contact:phone:+55 27 4020 5055","lat":-20.3643635,"lng":-40.3029047},{"id":"4530430673","name":"Fênix","tags":"amenity:nightclub","lat":-20.3640322,"lng":-40.3000983},{"id":"4530513549","name":"Impactus","tags":"shop:beauty","lat":-20.3637398,"lng":-40.2994237},{"id":"4814325960","name":"Instituto de Beleza Graça Coiffeur","tags":"addr:city:Vila Velha,addr:housenumber:1955,addr:postcode:29102-040,addr:street:Avenida Santa Leopoldina,addr:suburb:Coqueiral de Itaparica,phone:+55 27 3389 4938,shop:beauty","lat":-20.3670381,"lng":-40.3041373},{"id":"4814325962","name":"Pizza Mais Pré-Assada","tags":"addr:city:Vila Velha,addr:housenumber:1701 A,addr:postcode:29102-040,addr:street:Avenida Santa Leopoldina,addr:suburb:Coqueiral de Itaparica,amenity:restaurant,capacity:15,cuisine:pizza,delivery:yes,outdoor_seating:no,takeaway:only","lat":-20.3679419,"lng":-40.3046323},{"id":"4814346562","name":"Lava a Jato Vip Car","tags":"addr:city:Vila Velha,addr:housenumber:1925,addr:postcode:29102-040,addr:street:Avenida Santa Leopoldina,addr:suburb:Coqueiral de Itaparica,amenity:car_wash","lat":-20.3669632,"lng":-40.3040632},{"id":"4814346564","name":"Pizza Point","tags":"addr:city:Vila Velha,addr:housenumber:1825,addr:postcode:29102-040,addr:street:Avenida Santa Leopoldina,addr:suburb:Coqueiral de Itaparica,amenity:restaurant,capacity:15,cuisine:pizza,delivery:yes,outdoor_seating:yes,phone:+55 27 3329 9122,takeaway:yes","lat":-20.3659912,"lng":-40.3035136},{"id":"4867388851","name":"Drogarias Pacheco","tags":"addr:city:Vila Velha,addr:street:Avenida Santa Leopoldina,addr:suburb:Coqueiral de Itaparica,amenity:pharmacy,drive_through:no,operator:Drogarias Pacheco","lat":-20.3642671,"lng":-40.3028381},{"id":"5029143465","name":"Andrea's W&J Unissex","tags":"addr:city:Vila Velha,addr:street:Avenida Santa Leopoldina,addr:suburb:Coqueiral de Itaparica,shop:beauty","lat":-20.3678865,"lng":-40.30461},{"id":"6566159312","name":"Mercado Express","tags":"shop:convenience","lat":-20.3652583,"lng":-40.2994568},{"id":"6566159313","name":"Farmácia Santa Lúcia","tags":"amenity:pharmacy","lat":-20.3653897,"lng":-40.2995695},{"id":"7203328963","name":"Correios Praia de Itaparica","tags":"amenity:post_office","lat":-20.3638005,"lng":-40.3021055},{"id":"9521546822","name":"Spetaço Itaparica","tags":"amenity:bar,contact:facebook:spetaco.itaparica,contact:instagram:spetacochoperia,contact:mobile:+55 27 999206990","lat":-20.3635547,"lng":-40.302532},{"id":"9521546831","tags":"amenity:atm,brand:Banco24Horas","lat":-20.3637729,"lng":-40.3027332}]