[{"id":"1774210840","name":"HSBC","tags":"amenity:bank,brand:HSBC,brand:wikidata:Q190464,brand:wikipedia:en:HSBC","lat":-16.3738273,"lng":-39.5852685},{"id":"1774210844","tags":"amenity:pharmacy,healthcare:pharmacy","lat":-16.3728802,"lng":-39.5861161},{"id":"1774210848","tags":"amenity:pharmacy,healthcare:pharmacy","lat":-16.3744037,"lng":-39.5841742},{"id":"1774210849","name":"Bradesco","tags":"amenity:bank,brand:Bradesco,brand:wikidata:Q806181,brand:wikipedia:en:Banco Bradesco","lat":-16.374414,"lng":-39.5857084},{"id":"1774210851","tags":"amenity:bank","lat":-16.3747228,"lng":-39.5871997},{"id":"1774210853","tags":"amenity:pharmacy,healthcare:pharmacy","lat":-16.3742596,"lng":-39.5850539},{"id":"1774210859","tags":"amenity:pharmacy,healthcare:pharmacy","lat":-16.373117,"lng":-39.5855797},{"id":"1774210864","name":"Caixa Econ么mica Federal","tags":"amenity:bank,brand:Caixa Econ么mica Federal,brand:wikidata:Q835283,brand:wikipedia:pt:Caixa Econ么mica Federal","lat":-16.3748258,"lng":-39.5851398},{"id":"1774210868","tags":"amenity:pharmacy,healthcare:pharmacy","lat":-16.3745478,"lng":-39.5865131},{"id":"1774210871","tags":"amenity:pharmacy,healthcare:pharmacy","lat":-16.3741052,"lng":-39.584657},{"id":"1774210874","name":"Banco do Brasil","tags":"amenity:bank,brand:Banco do Brasil,brand:wikidata:Q610817,brand:wikipedia:en:Banco do Brasil","lat":-16.3738993,"lng":-39.5861805},{"id":"1774210878","tags":"shop:supermarket","lat":-16.373117,"lng":-39.5878649},{"id":"1774210880","tags":"amenity:pharmacy,healthcare:pharmacy","lat":-16.374342,"lng":-39.5853544},{"id":"1774210885","tags":"amenity:cafe","lat":-16.3743317,"lng":-39.5879078},{"id":"6007003385","name":"A s silva tourinho","tags":"addr:street:Avenida Dom Pedro II,shop:supermarket","lat":-16.3714368,"lng":-39.586284},{"id":"6007117785","name":"Coml bahiano de alimentos","tags":"addr:street:Rua Guaratinga,shop:supermarket","lat":-16.3733136,"lng":-39.5878133},{"id":"6128640485","name":"Dc dograria","tags":"addr:street:Avenida Porto Seguro,shop:supermarket","lat":-16.3744885,"lng":-39.5853776},{"id":"6128662785","name":"Ant么nia telina neta","tags":"shop:supermarket","lat":-16.3732417,"lng":-39.5858462},{"id":"6472357286","name":"3188 Maria stela Gomes de macedo","tags":"addr:housenumber:696,addr:street:Avenida Porto Seguro,name:en:Violeta perfumaria,shop:beauty","lat":-16.3749677,"lng":-39.5874599},{"id":"6472613186","name":"1700 Freire e Macedo ltda","tags":"addr:street:Avenida Dom Pedro II,name:en:Violeta perfumaria,shop:beauty","lat":-16.3739548,"lng":-39.5855863}]