[{"id":"5948702786","name":"Diomar dos santos dutra","tags":"addr:street:Rua Rodrigues Costa,shop:supermarket","lat":-14.6622386,"lng":-41.4915482},{"id":"5948782686","name":"Zilma viera dutra","tags":"addr:street:Praça,shop:supermarket","lat":-14.6622994,"lng":-41.4916733},{"id":"5948797085","name":"Aides Gonçalves","tags":"shop:supermarket","lat":-14.6624278,"lng":-41.4901915},{"id":"6538072385","name":"3656 patrícia dutra lima","tags":"shop:supermarket","lat":-14.6624022,"lng":-41.4900835},{"id":"6538075585","name":"4715 zilma viera dutra","tags":"addr:street:Praca,shop:supermarket","lat":-14.6623664,"lng":-41.4917991}]