[{"id":"2792713827","name":"Colégio O Delta","tags":"amenity:school","lat":-12.9860224,"lng":-38.4929721},{"id":"2792726146","name":"Academia de Ballet Ebateca","tags":"leisure:sports_centre","lat":-12.9896202,"lng":-38.4907415},{"id":"2792732083","name":"Brotas Center","tags":"addr:city:Salvador,addr:street:Avenida Dom João VI,addr:suburb:Brotas,shop:mall","lat":-12.9900698,"lng":-38.490999},{"id":"4517626901","name":"Valter's Fitness","tags":"addr:city:Salvador,addr:housenumber:23,addr:street:Ladeira do Acupe,contact:facebook:https://pt-br.facebook.com/valterfitnessacademia,contact:phone:+55 71 3035-4328,leisure:fitness_centre,opening_hours:Mo-Fr 05:00-23:00, Sa,Su 05:00-13:00,sport:gymnastics","lat":-12.9903171,"lng":-38.4931689},{"id":"6382307221","name":"Academia Podium","tags":"addr:city:SALVADOR,addr:housenumber:146,addr:postcode:40290700,addr:street:Avenida Dom João VI,addr:suburb:BROTAS,leisure:fitness_centre","lat":-12.9876754,"lng":-38.4925778},{"id":"6382307222","name":"Banco do Brasil","tags":"addr:city:SALVADOR,addr:housenumber:156,addr:postcode:40285000,addr:street:Avenida Dom João VI,addr:suburb:BROTAS,amenity:bank,brand:Banco do Brasil,brand:wikidata:Q610817,brand:wikipedia:en:Banco do Brasil","lat":-12.9870891,"lng":-38.4927177},{"id":"6382307223","name":"Extrafarma","tags":"addr:city:SALVADOR,addr:housenumber:158,addr:postcode:41285001,addr:street:Avenida Dom João VI,addr:suburb:BROTAS,amenity:pharmacy,brand:Extrafarma,brand:wikidata:Q20055480,brand:wikipedia:pt:Extrafarma,dispensing:yes,healthcare:pharmacy","lat":-12.9882062,"lng":-38.4926906},{"id":"6382307224","name":"ESQUINA DO ALMIRANTE","tags":"addr:city:SALVADOR,addr:housenumber:8,addr:postcode:40290-300,addr:street:Rua Almirante Amynthas Jorge,addr:suburb:ACUPE DE BROTAS,amenity:restaurant","lat":-12.9910788,"lng":-38.4940358},{"id":"7756886306","name":"Caixa Econômica Federal","tags":"amenity:bank,brand:Caixa Econômica Federal,brand:wikidata:Q835283,brand:wikipedia:pt:Caixa Econômica Federal","lat":-12.9896394,"lng":-38.4904609}]