[{"id":"3944419744","name":"Delegacia de Polícia Civil","tags":"addr:street:Rua Doutor Otto Tito,amenity:police,short_name:DPCA","lat":-5.1203155,"lng":-42.7955016},{"id":"9216155863","name":"Self Service Cubano","tags":"amenity:restaurant","lat":-5.1220306,"lng":-42.8023469},{"id":"9490701991","name":"Naah S - Nucleo De Atividades De Altas Habilidades - Superdotacao","tags":"amenity:school","lat":-5.12179,"lng":-42.7995734},{"id":"9490717268","name":"Centro De Habilitacao Ana Cordeiro","tags":"amenity:school","lat":-5.1215576,"lng":-42.7989538}]