[{"id":"2640625458","name":"Escola Moderna William Cartesius","tags":"addr:street:Avenida São Vicente de Paula,amenity:school","lat":-3.7671613,"lng":-38.6401873},{"id":"4202782694","name":"MFC","tags":"shop:supermarket","lat":-3.7658129,"lng":-38.6400341},{"id":"4510693098","name":"Fla Lanches","tags":"addr:street:Rua NW 6,amenity:restaurant,cuisine:diner;sandwich;ice_cream;pizza,name:pt:Fla Lanches,phone:+55 85 3475-3096","lat":-3.7650261,"lng":-38.6397229},{"id":"6604219223","name":"praça do terminal do araturi","tags":"leisure:park","lat":-3.7633668,"lng":-38.6397102},{"id":"6604226587","name":"Salão de beleza Alci cabeleireira","tags":"shop:beauty","lat":-3.7644086,"lng":-38.6404974}]